{
  "updated_at": "2026-06-11T02:47:28+09:00",
  "stocks": [
    {
      "code": "9867",
      "name": "SOLEKIA LIMITED",
      "name_jp": "ソレキア",
      "website": "https://www.solekia.com",
      "market": "スタンダード",
      "score": 60,
      "valuation_score": 16,
      "growth_score": 15,
      "shareholder_score": 9,
      "quality_score_detail": 11,
      "bonus_score": 1,
      "risk_penalty": -6,
      "forecast_adj": 0,
      "net_cash_ratio": 1.04,
      "per": 5.24,
      "market_cap_oku": 89.2,
      "dividend_yield": 0.69,
      "payout_ratio": 3.56,
      "roe": 9.73,
      "roic": 83.7,
      "pbr": 0.7,
      "ai_comment": "SOLEKIAは3期連続増収を達成し、最新四半期（FY2026/3期）では売上高+8.4%・営業利益+51.7%・純利益+57.4%と大幅な利益改善が確認される。売上トレンドは237.7→251.8→280.3億円と安定成長軌道にあり、業績の質が向上している点は評価できる。PERは約5.3倍と割安圏、PBRも0.7倍と資産価値に対して低評価。ただしROE9.73%は15%未満で資本効率に改善余地あり。ITサービス・システムインテグレーション系の中堅企業とみられ競争優位は限定的。NC比1.03はほぼ中立。財務健全性・流動性リスクは低いが、収益水準の低さと競争環境には注意が必要。",
      "risk_checks": {
        "roe_15_percent": false,
        "equity_ratio_50_percent": true,
        "debt_to_profit_5x": false,
        "fcf_stability": true,
        "liquidity_risk": false,
        "one_time_profit_risk": false
      },
      "trend_score": 10,
      "quality_score": 4,
      "chart_signals": {
        "volume_surge": false,
        "above_ma": true,
        "near_high": false
      },
      "tenbagger_stars": 3,
      "tab": "general",
      "theoretical_price": 27796.0,
      "upside_percent": 169.3
    },
    {
      "code": "7991",
      "name": "MAMIYA-OP CO LTD",
      "name_jp": "マミヤ・オーピー",
      "website": "https://www.mamiya-op.co.jp",
      "market": "スタンダード",
      "score": 58,
      "valuation_score": 16,
      "growth_score": 20,
      "shareholder_score": 8,
      "quality_score_detail": 15,
      "bonus_score": 1,
      "risk_penalty": -8,
      "forecast_adj": 0,
      "net_cash_ratio": 1.37,
      "per": 6.5,
      "market_cap_oku": 110.6,
      "dividend_yield": 4.66,
      "payout_ratio": 30.35,
      "roe": 18.79,
      "roic": 38.61,
      "pbr": 0.42,
      "ai_comment": "MAMIYA-OPは過去3期で売上が159→274→337億円と急拡大し、直近期も増収増益を達成。しかし最新四半期データ（2026年3月期）では売上が前年比-38%、営業利益-70.6%と急激な悪化が確認されており、成長トレンドが大きく転換している可能性が高い。PERは6.4倍、PBR0.42倍と割安感はあるが、ROE18.79%は高水準。NC比1.39はネットキャッシュの安定性を示す。産業機械・ゴルフ関連製品等を手がけるが事業の参入障壁は平均的。直近の業績急落は一時的要因か構造的悪化かの見極めが必要で、短期リスクは高い。",
      "risk_checks": {
        "roe_15_percent": true,
        "equity_ratio_50_percent": true,
        "debt_to_profit_5x": true,
        "fcf_stability": false,
        "liquidity_risk": false,
        "one_time_profit_risk": true
      },
      "trend_score": 2,
      "quality_score": 4,
      "chart_signals": {
        "volume_surge": false,
        "above_ma": false,
        "near_high": false
      },
      "tenbagger_stars": 5,
      "tab": "general",
      "theoretical_price": 4196.0,
      "upside_percent": 291.8
    },
    {
      "code": "4627",
      "name": "NATOCO CO LTD",
      "name_jp": "ナトコ",
      "website": "https://www.natoco.co.jp",
      "market": "スタンダード",
      "score": 57,
      "valuation_score": 14,
      "growth_score": 17,
      "shareholder_score": 9,
      "quality_score_detail": 9,
      "bonus_score": 2,
      "risk_penalty": -6,
      "forecast_adj": 0,
      "net_cash_ratio": 1.16,
      "per": 9.09,
      "market_cap_oku": 130.9,
      "dividend_yield": 3.13,
      "payout_ratio": 29.4,
      "roe": 4.66,
      "roic": 10.2,
      "pbr": 0.52,
      "ai_comment": "NATOCO CO LTDは塗料・コーティング材料メーカーとして安定した事業基盤を持つ。過去3期の売上は201.6→207.5→222.8億円と着実な増収トレンドを維持し、営業利益も前期比13.4%増と改善が進んでいる。最新四半期（2Q）では売上+4.5%、営業利益+33.5%、純利益+84.1%と大幅な増益を実現しており、業績モメンタムは良好。通期予想は売上230億円・営業利益14.5億円と引き続き増収増益見通し。PBR0.51倍と割安感があるが、ROE4.66%と収益性はやや低め。Basic Materialsセクターとして参入障壁は中程度であり、競争環境は平均的。財務的にはNC比1.17程度で過剰な負債リスクは低い。PER9倍台のバリュー株的特性を持つが、収益性向上が今後の課題となる。",
      "risk_checks": {
        "roe_15_percent": false,
        "equity_ratio_50_percent": true,
        "debt_to_profit_5x": false,
        "fcf_stability": true,
        "liquidity_risk": false,
        "one_time_profit_risk": false
      },
      "trend_score": 8,
      "quality_score": 4,
      "chart_signals": {
        "volume_surge": false,
        "above_ma": true,
        "near_high": true
      },
      "tenbagger_stars": 3,
      "tab": "general",
      "theoretical_price": 4713.0,
      "upside_percent": 172.1
    },
    {
      "code": "2449",
      "name": "PRAP JAPAN INC",
      "name_jp": "プラップジャパン",
      "website": "https://www.prap.co.jp",
      "market": "スタンダード",
      "score": 51,
      "valuation_score": 14,
      "growth_score": 13,
      "shareholder_score": 6,
      "quality_score_detail": 13,
      "bonus_score": 2,
      "risk_penalty": -6,
      "forecast_adj": 0,
      "net_cash_ratio": 1.04,
      "per": 9.73,
      "market_cap_oku": 46.0,
      "dividend_yield": 3.95,
      "payout_ratio": 38.65,
      "roe": 8.88,
      "roic": 67.84,
      "pbr": 0.85,
      "ai_comment": "PRAP JAPANは過去3期で売上が66.4→68.9→73.9億円と着実な増収トレンドを示し、直近年度の営業利益も25.4%増と高い伸びを記録している。しかし、最新四半期（2Q累計）では売上前年比+0.1%と伸びが急減速し、営業利益は-15.6%と大幅減益に転じており、業績トレンドの勢いが失われつつある点が懸念材料。通期予想は売上81億円・営業利益8.12億円と上積みを見込むが、上半期の落ち込みを踏まえると達成ハードルは高い。PBR0.85倍・PER9.7倍と割安感はあるが、ROE8.88%は水準としてやや物足りない。PRは競合多数で参入障壁が低く、事業の質は平均的。流動性リスクは低いものの、収益の安定性に課題が残る。",
      "risk_checks": {
        "roe_15_percent": false,
        "equity_ratio_50_percent": true,
        "debt_to_profit_5x": false,
        "fcf_stability": true,
        "liquidity_risk": false,
        "one_time_profit_risk": false
      },
      "trend_score": 5,
      "quality_score": 4,
      "chart_signals": {
        "volume_surge": false,
        "above_ma": false,
        "near_high": false
      },
      "tenbagger_stars": 2,
      "tab": "general",
      "theoretical_price": 2231.0,
      "upside_percent": 116.2
    },
    {
      "code": "8135",
      "name": "ZETT CORPORATION",
      "name_jp": "ゼット",
      "website": "https://zett.jp",
      "market": "スタンダード",
      "score": 51,
      "valuation_score": 14,
      "growth_score": 13,
      "shareholder_score": 8,
      "quality_score_detail": 10,
      "bonus_score": 2,
      "risk_penalty": -7,
      "forecast_adj": 0,
      "net_cash_ratio": 1.33,
      "per": 8.24,
      "market_cap_oku": 80.5,
      "dividend_yield": 8.78,
      "payout_ratio": 36.11,
      "roe": 20.56,
      "roic": 19.64,
      "pbr": 0.52,
      "ai_comment": "ZETT CORPORATIONはスポーツ用品メーカーとして野球用品を中心に展開。売上は3期連続で増収（498.9→519.6→553.1億円）を達成し、営業利益も22.2%増と好調な推移を示している。最新四半期（2026年3月期通期）では売上+6.0%・営業利益+16.7%と増収増益を維持しているが、純利益が-67.4%と大幅減益となっており、一時的な特殊損益の影響が懸念される。PBR0.52倍・PER8.2倍と割安水準にあり、ROE20.56%と高収益性を示す。ただし純利益の大幅下落はリスク要因であり、継続的な業績モニタリングが必要。スポーツ用品市場は競合も多く、質スコアは中程度の評価となる。",
      "risk_checks": {
        "roe_15_percent": true,
        "equity_ratio_50_percent": false,
        "debt_to_profit_5x": true,
        "fcf_stability": true,
        "liquidity_risk": false,
        "one_time_profit_risk": true
      },
      "trend_score": 7,
      "quality_score": 4,
      "chart_signals": {
        "volume_surge": false,
        "above_ma": false,
        "near_high": false
      },
      "tenbagger_stars": 3,
      "tab": "general",
      "theoretical_price": 1188.0,
      "upside_percent": 189.0
    },
    {
      "code": "6497",
      "name": "HAMAI INDUSTRIES",
      "name_jp": "ハマイ",
      "website": "https://www.hamai-net.com",
      "market": "スタンダード",
      "score": 50,
      "valuation_score": 14,
      "growth_score": 13,
      "shareholder_score": 7,
      "quality_score_detail": 9,
      "bonus_score": 2,
      "risk_penalty": -6,
      "forecast_adj": 0,
      "net_cash_ratio": 1.17,
      "per": 9.26,
      "market_cap_oku": 89.8,
      "dividend_yield": 3.38,
      "payout_ratio": 27.65,
      "roe": 5.67,
      "roic": 9.43,
      "pbr": 0.52,
      "ai_comment": "HAMAI INDUSTRIESは売上が3期連続で増収傾向（111.3→120.9→127.2億円）を維持しており、直近期も売上+5.1%・営業利益+9.4%と安定した成長を示す。ただし最新1Q（2026年1-3月）では営業利益が前年同期比-9.1%と減益に転じており、通期予想（売上131億円・営業利益12.5億円）は保守的な設定に留まる。PBR0.51倍・PER9.1倍と割安感があるが、ROE5.67%は低水準。NC比1.18は財務健全性を示す。産業機械系の事業特性上、競争優位は限定的で収益変動リスクもある。1Q減益トレンドを踏まえると慎重な姿勢が必要。",
      "risk_checks": {
        "roe_15_percent": false,
        "equity_ratio_50_percent": true,
        "debt_to_profit_5x": false,
        "fcf_stability": true,
        "liquidity_risk": false,
        "one_time_profit_risk": false
      },
      "trend_score": 7,
      "quality_score": 4,
      "chart_signals": {
        "volume_surge": false,
        "above_ma": true,
        "near_high": false
      },
      "tenbagger_stars": 2,
      "tab": "general",
      "theoretical_price": 3636.0,
      "upside_percent": 171.3
    },
    {
      "code": "4624",
      "name": "ISAMU PAINT CO",
      "name_jp": "イサム塗料",
      "website": "https://www.isamu.co.jp",
      "market": "スタンダード",
      "score": 49,
      "valuation_score": 17,
      "growth_score": 14,
      "shareholder_score": 6,
      "quality_score_detail": 5,
      "bonus_score": 2,
      "risk_penalty": -6,
      "forecast_adj": 0,
      "net_cash_ratio": 1.55,
      "per": 8.96,
      "market_cap_oku": 67.6,
      "dividend_yield": 1.39,
      "payout_ratio": 12.62,
      "roe": 3.19,
      "roic": 4.77,
      "pbr": 0.37,
      "ai_comment": "ISAMU PAINT COは塗料メーカーとして3期連続増収を達成しており、売上トレンドは安定的に拡大している。直近期は売上+2.0%と緩やかな増収だが、営業利益は-2.8%と微減益。ただし最新四半期データ（2026年3月期）では売上+3.0%・営業利益+45.7%・純利益+37.5%と大幅改善が確認されており、収益性の回復が鮮明。PBR0.39倍・PER9.2倍と割安感が強く、NC比1.5倍超でネットキャッシュ保有も財務安定性を示す。一方ROE3.19%は低水準で資本効率に課題あり。塗料市場は競合多く差別化が難しいが、一定の技術力と顧客基盤を持つ中堅メーカーとして安定した事業継続が見込まれる。",
      "risk_checks": {
        "roe_15_percent": false,
        "equity_ratio_50_percent": true,
        "debt_to_profit_5x": false,
        "fcf_stability": true,
        "liquidity_risk": false,
        "one_time_profit_risk": false
      },
      "trend_score": 7,
      "quality_score": 4,
      "chart_signals": {
        "volume_surge": false,
        "above_ma": false,
        "near_high": false
      },
      "tenbagger_stars": 2,
      "tab": "general",
      "theoretical_price": 12329.0,
      "upside_percent": 247.3
    },
    {
      "code": "7434",
      "name": "OTAKE CORP",
      "name_jp": "オータケ",
      "website": "https://www.kk-otake.co.jp",
      "market": "スタンダード",
      "score": 49,
      "valuation_score": 16,
      "growth_score": 12,
      "shareholder_score": 9,
      "quality_score_detail": 2,
      "bonus_score": 1,
      "risk_penalty": -5,
      "forecast_adj": 0,
      "net_cash_ratio": 1.29,
      "per": 7.24,
      "market_cap_oku": 68.4,
      "dividend_yield": 2.32,
      "payout_ratio": 15.37,
      "roe": 5.56,
      "roic": 7.69,
      "pbr": 0.4,
      "ai_comment": "OTAKE CORPは3期連続で売上が増加（293.2→312.5→329.9億円）し、直近の3Q累計でも売上前年比+8.0%、営業利益+13.1%と加速傾向にある。通期予想は売上340億円・営業利益10億円と堅調。ただしPBR0.39倍・ROE5.56%と資本効率は低く、収益性の改善余地は大きい。産業向けサービス系の事業モデルで参入障壁は中程度。PER7.1倍と割安感はあるが、利益率の薄さと低ROEがバリュエーション低迷の要因。財務面ではNC比1.31と一定の有利子負債があり注意が必要。中長期的な収益性向上が課題だが、増収増益トレンドの継続は評価できる。",
      "risk_checks": {
        "roe_15_percent": false,
        "equity_ratio_50_percent": false,
        "debt_to_profit_5x": true,
        "fcf_stability": true,
        "liquidity_risk": false,
        "one_time_profit_risk": false
      },
      "trend_score": 10,
      "quality_score": 4,
      "chart_signals": {
        "volume_surge": false,
        "above_ma": false,
        "near_high": false
      },
      "tenbagger_stars": 2,
      "tab": "general",
      "theoretical_price": 5215.0,
      "upside_percent": 199.0
    },
    {
      "code": "5956",
      "name": "TOSO CO LTD",
      "name_jp": "トーソー",
      "website": "https://www.toso.co.jp",
      "market": "スタンダード",
      "score": 48,
      "valuation_score": 19,
      "growth_score": 13,
      "shareholder_score": 9,
      "quality_score_detail": 1,
      "bonus_score": 1,
      "risk_penalty": -6,
      "forecast_adj": 0,
      "net_cash_ratio": 1.97,
      "per": 7.4,
      "market_cap_oku": 49.6,
      "dividend_yield": 2.35,
      "payout_ratio": 20.45,
      "roe": 3.4,
      "roic": 6.95,
      "pbr": 0.31,
      "ai_comment": "トスコ（TOSO CO LTD）はブラインド・カーテンレール等の窓装飾メーカーで、国内シェアは安定しているが市場は成熟。直近本決算（FY2026/3期）は売上+2.0%・営業利益+28.0%・純利益+34.2%と増収増益を継続。過去3期の売上も213→216→228→232億円と右肩上がりであり業績トレンドは良好。ただし営業利益率は約4%と薄利で収益基盤の脆弱さは否めない。PBR0.31倍・PER7.2倍と割安感は強いが、ROE3.4%と資本効率は低水準。NC比2.0は財務健全性を示す。窓装飾市場の成熟・建築着工件数依存・競合との価格競争がリスク要因。",
      "risk_checks": {
        "roe_15_percent": false,
        "equity_ratio_50_percent": true,
        "debt_to_profit_5x": false,
        "fcf_stability": true,
        "liquidity_risk": false,
        "one_time_profit_risk": false
      },
      "trend_score": 7,
      "quality_score": 4,
      "chart_signals": {
        "volume_surge": false,
        "above_ma": false,
        "near_high": false
      },
      "tenbagger_stars": 2,
      "tab": "general",
      "theoretical_price": 1973.0,
      "upside_percent": 251.6
    },
    {
      "code": "5753",
      "name": "NIPPON SHINDO CO",
      "name_jp": "日本伸銅",
      "website": "https://www.nippon-shindo.co.jp",
      "market": "スタンダード",
      "score": 47,
      "valuation_score": 19,
      "growth_score": 9,
      "shareholder_score": 6,
      "quality_score_detail": 13,
      "bonus_score": 2,
      "risk_penalty": -13,
      "forecast_adj": 0,
      "net_cash_ratio": 1.89,
      "per": 6.53,
      "market_cap_oku": 48.4,
      "dividend_yield": 0.88,
      "payout_ratio": 4.32,
      "roe": 8.1,
      "roic": 15.66,
      "pbr": 1.11,
      "ai_comment": "NIPPON SHINDOは直近四半期（FY2026/3期）で売上+15.4%・営業利益+46.8%と大幅増収増益を達成しており、業績モメンタムは良好。ただし純利益は-23.0%と減少しており、一時的な特別損失等の影響が示唆される。過去3期売上推移は272.4→233.4→261.2億円と一度落ち込んだ後に回復基調。PER6.5倍・PBR1.11倍と割安感があり、ROE8.1%は平均水準。銅線・伸銅品等の基礎素材メーカーとして市況に収益が左右されやすく、競争優位性は限定的。NC比1.89と財務健全性は概ね良好。純利益の一過性リスクと市況依存リスクに留意が必要。",
      "risk_checks": {
        "roe_15_percent": false,
        "equity_ratio_50_percent": true,
        "debt_to_profit_5x": true,
        "fcf_stability": false,
        "liquidity_risk": false,
        "one_time_profit_risk": true
      },
      "trend_score": 7,
      "quality_score": 4,
      "chart_signals": {
        "volume_surge": false,
        "above_ma": false,
        "near_high": false
      },
      "tenbagger_stars": 2,
      "tab": "general",
      "theoretical_price": 5376.0,
      "upside_percent": 137.1
    },
    {
      "code": "3388",
      "name": "MEIJI ELECTRIC INDUSTRIES CO LT",
      "name_jp": "明治電機工業",
      "website": "https://www.meijidenki.co.jp",
      "market": "プライム",
      "score": 47,
      "valuation_score": 14,
      "growth_score": 14,
      "shareholder_score": 8,
      "quality_score_detail": 5,
      "bonus_score": 1,
      "risk_penalty": -6,
      "forecast_adj": 0,
      "net_cash_ratio": 1.06,
      "per": 9.05,
      "market_cap_oku": 254.3,
      "dividend_yield": 4.77,
      "payout_ratio": 40.33,
      "roe": 7.08,
      "roic": 12.44,
      "pbr": 0.68,
      "ai_comment": "明治電機工業は3期連続で増収を達成し、直近期も営業利益率が改善傾向にある。過去3期の売上推移は709.5→745.8→786.7億円と安定成長。ただし最新四半期データ（2026年3月期）では売上が前年比▲2.9%と減収に転じており、トレンドに注意が必要。営業利益は+11.4%と改善しており収益性向上は評価できる。電気設備・産業用電機の専門商社として一定の市場基盤を持つが、同業他社との競争は激しく参入障壁は中程度。PBR0.68倍・PER9倍と割安感があるが、ROE7%台は改善余地あり。財務健全性は概ね良好だが、売上反転には注視が必要。",
      "risk_checks": {
        "roe_15_percent": false,
        "equity_ratio_50_percent": true,
        "debt_to_profit_5x": false,
        "fcf_stability": true,
        "liquidity_risk": false,
        "one_time_profit_risk": false
      },
      "trend_score": 7,
      "quality_score": 4,
      "chart_signals": {
        "volume_surge": false,
        "above_ma": false,
        "near_high": false
      },
      "tenbagger_stars": 3,
      "tab": "general",
      "theoretical_price": 3982.0,
      "upside_percent": 97.3
    },
    {
      "code": "5697",
      "name": "SANYU CO LTD",
      "name_jp": "サンユウ",
      "website": "https://www.sanyu-cfs.co.jp",
      "market": "スタンダード",
      "score": 46,
      "valuation_score": 16,
      "growth_score": 10,
      "shareholder_score": 9,
      "quality_score_detail": 3,
      "bonus_score": 3,
      "risk_penalty": -6,
      "forecast_adj": 0,
      "net_cash_ratio": 1.31,
      "per": 6.78,
      "market_cap_oku": 41.5,
      "dividend_yield": 8.73,
      "payout_ratio": 29.64,
      "roe": 4.58,
      "roic": 9.54,
      "pbr": 0.4,
      "ai_comment": "SANYU CO LTDは基礎素材セクターの企業で、直近四半期（2026年3月期）の開示では売上高+4.6%、営業利益+32.6%、純利益+35.8%と大幅な増益を記録しており、業績トレンドは良好。過去3期の売上推移も239.4→240.1→244.4億円と緩やかながら連続増収基調にある。PERは約6.8倍、PBRは0.4倍と割安感が強く、NC比1.30は財務健全性を示す。一方ROEは4.58%と低水準で資本効率に課題が残る。基礎素材業界は景気敏感度が高く競争も激しいが、直近の収益改善は評価できる。中長期的な収益安定性と資本効率改善が課題。",
      "risk_checks": {
        "roe_15_percent": false,
        "equity_ratio_50_percent": true,
        "debt_to_profit_5x": false,
        "fcf_stability": true,
        "liquidity_risk": false,
        "one_time_profit_risk": false
      },
      "trend_score": 7,
      "quality_score": 4,
      "chart_signals": {
        "volume_surge": false,
        "above_ma": false,
        "near_high": false
      },
      "tenbagger_stars": 2,
      "tab": "general",
      "theoretical_price": 2097.0,
      "upside_percent": 205.7
    },
    {
      "code": "5819",
      "name": "CANARE ELECTRIC CO",
      "name_jp": "カナレ電気",
      "website": "https://www.canare.co.jp",
      "market": "スタンダード",
      "score": 46,
      "valuation_score": 14,
      "growth_score": 7,
      "shareholder_score": 5,
      "quality_score_detail": 11,
      "bonus_score": 2,
      "risk_penalty": -2,
      "forecast_adj": 0,
      "net_cash_ratio": 1.28,
      "per": 9.9,
      "market_cap_oku": 119.1,
      "dividend_yield": 3.8,
      "payout_ratio": 37.56,
      "roe": 6.3,
      "roic": 16.18,
      "pbr": 0.62,
      "ai_comment": "カナレ電気は放送・通信向けケーブル等の専門メーカーで一定の競争優位を持つが、最新1Q（2026年1-3月）では売上-3.6%、営業利益-25.2%、純利益-29.7%と大幅な減益となっており、通期予想も営業利益1,480百万円（前期15.8億円から実質横ばい〜微減水準）と慎重。過去3期の売上推移は128.7→123.8→131.1億円と回復基調にあったものの、直近四半期の落ち込みが懸念材料。PBR0.61倍・PER9.7倍と割安感はあるが、ROE6.3%は低水準でNC比1.3と財務は健全。短期的な業績悪化リスクを重視し、トレンドスコアは引き下げる。",
      "risk_checks": {
        "roe_15_percent": false,
        "equity_ratio_50_percent": true,
        "debt_to_profit_5x": true,
        "fcf_stability": true,
        "liquidity_risk": false,
        "one_time_profit_risk": false
      },
      "trend_score": 2,
      "quality_score": 7,
      "chart_signals": {
        "volume_surge": false,
        "above_ma": false,
        "near_high": false
      },
      "tenbagger_stars": 2,
      "tab": "general",
      "theoretical_price": 4055.0,
      "upside_percent": 132.9
    },
    {
      "code": "8138",
      "name": "SANKYO KASEI CORP",
      "name_jp": "三京化成",
      "website": "https://www.sankyokasei-corp.co.jp",
      "market": "スタンダード",
      "score": 45,
      "valuation_score": 21,
      "growth_score": 11,
      "shareholder_score": 6,
      "quality_score_detail": 2,
      "bonus_score": 0,
      "risk_penalty": -6,
      "forecast_adj": 0,
      "net_cash_ratio": 1.63,
      "per": 4.82,
      "market_cap_oku": 36.3,
      "dividend_yield": 2.48,
      "payout_ratio": 11.95,
      "roe": 7.22,
      "roic": 6.41,
      "pbr": 0.4,
      "ai_comment": "三共化成工業は素材・化学セクターの中堅企業。直近期（2026年3月期）は売上+0.3%、営業利益+10.6%、純利益+19.6%と増収増益基調を維持。過去3期の売上推移は267→262→271→272億円と緩やかな回復傾向にある。営業利益率は約1.9%と依然薄く、収益性の改善余地が大きい課題。PBRは0.39倍と著しく割安であり、PER4.8倍も低水準。ROE7.2%はやや物足りないが改善方向にある。NC比1.64倍は財務健全性を示す。化成品分野は競争が激しく差別化が難しいが、安定的な顧客基盤を持つとみられる。利益改善トレンドは評価できるが、薄利体質とセクター特性から事業の質は平均的と判断。",
      "risk_checks": {
        "roe_15_percent": false,
        "equity_ratio_50_percent": true,
        "debt_to_profit_5x": false,
        "fcf_stability": true,
        "liquidity_risk": false,
        "one_time_profit_risk": false
      },
      "trend_score": 7,
      "quality_score": 4,
      "chart_signals": {
        "volume_surge": false,
        "above_ma": false,
        "near_high": false
      },
      "tenbagger_stars": 3,
      "tab": "general",
      "theoretical_price": 14196.0,
      "upside_percent": 251.8
    },
    {
      "code": "8046",
      "name": "MARUFUJI SHEET PILING CO",
      "name_jp": "丸藤シートパイル",
      "website": "https://www.mrfj.co.jp",
      "market": "スタンダード",
      "score": 45,
      "valuation_score": 16,
      "growth_score": 10,
      "shareholder_score": 8,
      "quality_score_detail": 1,
      "bonus_score": 3,
      "risk_penalty": -6,
      "forecast_adj": 0,
      "net_cash_ratio": 1.45,
      "per": 7.5,
      "market_cap_oku": 143.1,
      "dividend_yield": 9.21,
      "payout_ratio": 34.36,
      "roe": 4.96,
      "roic": 6.12,
      "pbr": 0.44,
      "ai_comment": "マルフジ鋼業は直近四半期（2026年3月期）で売上高+13.4%、営業利益+33.6%、純利益+28.1%と大幅な増収増益を達成しており、業績トレンドは明確に改善方向。過去3期の売上推移も351→345→356億円と底堅く回復しつつある。建設・土木向け鋼矢板・鋼管杭の専業メーカーとして一定の市場地位を持つが、公共事業依存度が高く景気・予算動向に左右されやすい点はリスク。PBR0.45倍・PER7.4倍と割安圏にあるが、ROE4.96%と資本効率は低水準。NC比1.46は財務安定性を示すが、収益性向上が課題。インフラ更新需要の取り込みが今後の鍵となる。",
      "risk_checks": {
        "roe_15_percent": false,
        "equity_ratio_50_percent": true,
        "debt_to_profit_5x": false,
        "fcf_stability": true,
        "liquidity_risk": false,
        "one_time_profit_risk": false
      },
      "trend_score": 9,
      "quality_score": 4,
      "chart_signals": {
        "volume_surge": false,
        "above_ma": false,
        "near_high": false
      },
      "tenbagger_stars": 3,
      "tab": "general",
      "theoretical_price": 2695.0,
      "upside_percent": 224.7
    },
    {
      "code": "6797",
      "name": "NAGOYA ELECTRIC WORKS",
      "name_jp": "名古屋電機工業",
      "website": "https://www.nagoya-denki.co.jp",
      "market": "スタンダード",
      "score": 44,
      "valuation_score": 14,
      "growth_score": 10,
      "shareholder_score": 5,
      "quality_score_detail": 13,
      "bonus_score": 2,
      "risk_penalty": -6,
      "forecast_adj": 0,
      "net_cash_ratio": 1.08,
      "per": 8.98,
      "market_cap_oku": 136.5,
      "dividend_yield": 7.77,
      "payout_ratio": 34.82,
      "roe": 9.85,
      "roic": 15.33,
      "pbr": 0.57,
      "ai_comment": "名古屋電機工業は直近四半期(FY2026/3期)で売上+0.3%とほぼ横ばいながら、営業利益-36.4%・純利益-31.2%と大幅な減益となっており、過去3期の売上も180→175→172億円と減少傾向が継続。事業はインフラ系の道路情報板・交通信号システム等で一定の参入障壁があるものの、公共投資依存で競合も存在し質は平均的。PERは9倍台と割安、PBR0.57倍は資産価値に対し低評価。ROEは9.85%と中程度だが今期の大幅減益で悪化懸念。財務健全性は概ね良好だが、収益のボラティリティと減益継続リスクに注意が必要。",
      "risk_checks": {
        "roe_15_percent": false,
        "equity_ratio_50_percent": true,
        "debt_to_profit_5x": true,
        "fcf_stability": false,
        "liquidity_risk": false,
        "one_time_profit_risk": false
      },
      "trend_score": 2,
      "quality_score": 4,
      "chart_signals": {
        "volume_surge": false,
        "above_ma": false,
        "near_high": true
      },
      "tenbagger_stars": 3,
      "tab": "general",
      "theoretical_price": 3282.0,
      "upside_percent": 182.6
    },
    {
      "code": "3710",
      "name": "JORUDAN CO LTD",
      "name_jp": "ジョルダン",
      "website": "https://www.jorudan.co.jp",
      "market": "スタンダード",
      "score": 40,
      "valuation_score": 14,
      "growth_score": 10,
      "shareholder_score": 9,
      "quality_score_detail": 1,
      "bonus_score": 1,
      "risk_penalty": -6,
      "forecast_adj": 0,
      "net_cash_ratio": 1.13,
      "per": 8.57,
      "market_cap_oku": 30.5,
      "dividend_yield": 1.01,
      "payout_ratio": 8.61,
      "roe": 5.71,
      "roic": 3.38,
      "pbr": 0.63,
      "ai_comment": "ジョルダンは乗換案内を中核とするITサービス企業。直近年次では売上が3期連続で緩やかに減少しているが、最新四半期（2Q累計）では売上+11.3%・営業利益+93.3%と急回復しており、通期予想も増収増益見通し。ROEは5.71%と低水準でROE15%基準は未達。PBRは0.64倍と割安圏だがNC比1.1と財務は健全。競争優位性は乗換案内という認知度の高いブランドがあるものの、Google・ヤフーなどとの競合が激しく収益の安定性に課題。一時的な利益貢献（純利益2.6億円に対し営業利益0.5億円の乖離）に注意が必要。四半期ベースでの業績回復を評価しつつも、継続的な収益拡大の確認が重要。",
      "risk_checks": {
        "roe_15_percent": false,
        "equity_ratio_50_percent": true,
        "debt_to_profit_5x": true,
        "fcf_stability": true,
        "liquidity_risk": false,
        "one_time_profit_risk": true
      },
      "trend_score": 7,
      "quality_score": 4,
      "chart_signals": {
        "volume_surge": false,
        "above_ma": false,
        "near_high": false
      },
      "tenbagger_stars": 3,
      "tab": "general",
      "theoretical_price": 1446.0,
      "upside_percent": 142.3
    },
    {
      "code": "3134",
      "name": "HAMEE CORP",
      "name_jp": "Ｈａｍｅｅ",
      "website": "https://hamee.co.jp",
      "market": "スタンダード",
      "score": 39,
      "valuation_score": 16,
      "growth_score": 19,
      "shareholder_score": 8,
      "quality_score_detail": 14,
      "bonus_score": 2,
      "risk_penalty": -26,
      "forecast_adj": 0,
      "net_cash_ratio": 1.08,
      "per": 7.13,
      "market_cap_oku": 65.1,
      "dividend_yield": 5.51,
      "payout_ratio": 39.39,
      "roe": 12.09,
      "roic": 42.21,
      "pbr": 0.9,
      "ai_comment": "HAMEEは過去3期で売上140→176→229億円と高成長を示しており年間トレンドは良好だが、最新四半期（3Q累計）では売上前年比-2.4%、営業利益-58.8%、純利益-72.2%と急激な業績悪化が確認される。通期予想でも営業利益723百万円と前期比大幅減益見通しであり、直近のモメンタムは著しく悪化している。PERは7倍台と割安感があるが、PBRは1倍割れでROEも12%と目標水準を下回る。スマホアクセサリー等のコンシューマー向けEC事業は競争激化が続き、収益の安定性に懸念がある。短期的なリスクは高まっており、業績悪化の根本要因の見極めが重要。",
      "risk_checks": {
        "roe_15_percent": false,
        "equity_ratio_50_percent": false,
        "debt_to_profit_5x": false,
        "fcf_stability": false,
        "liquidity_risk": true,
        "one_time_profit_risk": false
      },
      "trend_score": 2,
      "quality_score": 4,
      "chart_signals": {
        "volume_surge": false,
        "above_ma": false,
        "near_high": false
      },
      "tenbagger_stars": 4,
      "tab": "general",
      "theoretical_price": 1046.0,
      "upside_percent": 157.0
    },
    {
      "code": "3176",
      "name": "SANYO TRADING CO LIMITED",
      "name_jp": "三洋貿易",
      "website": "https://sanyo-trading.co.jp",
      "market": "プライム",
      "score": 39,
      "valuation_score": 14,
      "growth_score": 6,
      "shareholder_score": 8,
      "quality_score_detail": 11,
      "bonus_score": 1,
      "risk_penalty": -12,
      "forecast_adj": 0,
      "net_cash_ratio": 1.0,
      "per": 9.87,
      "market_cap_oku": 433.5,
      "dividend_yield": 2.98,
      "payout_ratio": 38.72,
      "roe": 8.99,
      "roic": 15.26,
      "pbr": 0.8,
      "ai_comment": "三洋貿易は産業機械・化学品等を扱う専門商社。売上は3期連続増収（1205→1293→1327億円）と堅調だが、直近期の営業利益は前期比-14.8%と減益となっている。一方、直近四半期（2Q）では売上+3.1%・営業利益+8.8%・純利益+6.0%と回復基調が鮮明で、通期予想は売上1330億円・営業利益65億円。PER約9.8倍・PBR0.79倍と割安感があり、ROEは約9%と平均水準。専門商社として一定のニッチ領域での競争優位はあるが、参入障壁は限定的。NC比1.0064と財務健全性は概ね良好。増収継続と四半期回復を評価するが、営業利益率が低水準（約4.5%）であり収益性向上が課題。",
      "risk_checks": {
        "roe_15_percent": false,
        "equity_ratio_50_percent": false,
        "debt_to_profit_5x": false,
        "fcf_stability": true,
        "liquidity_risk": false,
        "one_time_profit_risk": false
      },
      "trend_score": 7,
      "quality_score": 4,
      "chart_signals": {
        "volume_surge": false,
        "above_ma": false,
        "near_high": false
      },
      "tenbagger_stars": 1,
      "tab": "general",
      "theoretical_price": 2973.0,
      "upside_percent": 97.7
    },
    {
      "code": "6335",
      "name": "TOKYO KIKAI SEISAKUSHO",
      "name_jp": "東京機械製作所",
      "website": "https://www.tks-net.co.jp",
      "market": "スタンダード",
      "score": 38,
      "valuation_score": 21,
      "growth_score": 5,
      "shareholder_score": 3,
      "quality_score_detail": 10,
      "bonus_score": 1,
      "risk_penalty": -13,
      "forecast_adj": 0,
      "net_cash_ratio": 1.51,
      "per": 4.05,
      "market_cap_oku": 42.2,
      "dividend_yield": 0.0,
      "payout_ratio": 0.0,
      "roe": 4.24,
      "roic": 100.0,
      "pbr": 0.46,
      "ai_comment": "直近四半期（FY2026/3期）では売上高8,456百万円（前期比+14.3%）、営業利益721百万円（+12.5%）、純利益1,057百万円（+206.4%）と大幅回復。過去3期の売上推移（87.7→93.2→74.0億円）では一時的な落ち込みがあったが、最新期で増収増益に転じており業績モメンタムは改善傾向。PERは約4.5倍と極めて割安で、PBR0.51倍も解散価値以下。NC比1.33はネットキャッシュ超過を示し財務健全性は高い。ただしROE4.24%は低水準で資本効率の改善が課題。新聞印刷機械メーカーとして市場縮小リスクは続くが、ニッチな競争優位と手厚い財務基盤が下値を支える。",
      "risk_checks": {
        "roe_15_percent": false,
        "equity_ratio_50_percent": true,
        "debt_to_profit_5x": false,
        "fcf_stability": true,
        "liquidity_risk": false,
        "one_time_profit_risk": true
      },
      "trend_score": 7,
      "quality_score": 4,
      "chart_signals": {
        "volume_surge": false,
        "above_ma": true,
        "near_high": false
      },
      "tenbagger_stars": 2,
      "tab": "general",
      "theoretical_price": 1870.0,
      "upside_percent": 252.3
    },
    {
      "code": "5984",
      "name": "KANEFUSA CORP",
      "name_jp": "兼房",
      "website": "https://www.kanefusa.co.jp",
      "market": "スタンダード",
      "score": 38,
      "valuation_score": 14,
      "growth_score": 5,
      "shareholder_score": 8,
      "quality_score_detail": 3,
      "bonus_score": 3,
      "risk_penalty": -6,
      "forecast_adj": 0,
      "net_cash_ratio": 1.27,
      "per": 9.75,
      "market_cap_oku": 100.6,
      "dividend_yield": 3.17,
      "payout_ratio": 35.02,
      "roe": 3.22,
      "roic": 2.93,
      "pbr": 0.32,
      "ai_comment": "カネフサは切削工具・丸のこ刃等の製造メーカーで一定のニッチ競争優位を持つ。直近四半期（2026年3月期通期）では売上+3.5%・営業利益+45.9%と大幅改善が確認され、トレンドは底打ち反転の兆し。ただし過去3期の売上推移は211→201→202億円と低迷が続いており、構造的な成長力には課題が残る。PBR0.32倍・PER9.6倍と割安感は強いが、ROE3.22%と資本効率は低水準。NC比1.29は財務健全性を示す。切削工具市場は競争激化かつ景気敏感セクターであり、利益の振れ幅が大きい点はリスク。四半期データの改善を踏まえ業績トレンドは上方修正傾向と判断。",
      "risk_checks": {
        "roe_15_percent": false,
        "equity_ratio_50_percent": true,
        "debt_to_profit_5x": false,
        "fcf_stability": true,
        "liquidity_risk": false,
        "one_time_profit_risk": false
      },
      "trend_score": 7,
      "quality_score": 4,
      "chart_signals": {
        "volume_surge": false,
        "above_ma": false,
        "near_high": false
      },
      "tenbagger_stars": 2,
      "tab": "general",
      "theoretical_price": 2789.0,
      "upside_percent": 285.3
    },
    {
      "code": "9876",
      "name": "COX CO LTD",
      "name_jp": "コックス",
      "website": "https://www.cox-online.co.jp",
      "market": "スタンダード",
      "score": 37,
      "valuation_score": 16,
      "growth_score": 0,
      "shareholder_score": 6,
      "quality_score_detail": 14,
      "bonus_score": 1,
      "risk_penalty": -6,
      "forecast_adj": 0,
      "net_cash_ratio": 1.15,
      "per": 5.73,
      "market_cap_oku": 61.0,
      "dividend_yield": 0.0,
      "payout_ratio": 0.0,
      "roe": 10.14,
      "roic": 21.62,
      "pbr": 0.58,
      "ai_comment": "COX CO LTDは直近期（2026年2月期）で売上高が前期比-2.3%と減収ながら、営業利益は+4.8%と増益を確保した。コスト管理の改善が見られるものの、純利益は-10.7%と減少しており、一過性要因または税負担増の可能性がある。過去3期の売上推移は148.9→153.0→149.6と増収後に反落しており、成長の継続性に疑問符がつく。PERは5.75倍と割安水準、PBRも0.58倍と純資産を大きく下回り市場の評価は低い。ROEは10.14%とまずまずだが15%には届かない。消費者向けアパレル関連セクターは競争が激しく、参入障壁は低め。NC比1.14は財務的には安定圏内。バリュー株的魅力はあるが成長ドライバーが不明確で慎重な見方が必要。",
      "risk_checks": {
        "roe_15_percent": false,
        "equity_ratio_50_percent": true,
        "debt_to_profit_5x": true,
        "fcf_stability": true,
        "liquidity_risk": false,
        "one_time_profit_risk": true
      },
      "trend_score": 2,
      "quality_score": 4,
      "chart_signals": {
        "volume_surge": false,
        "above_ma": false,
        "near_high": false
      },
      "tenbagger_stars": 2,
      "tab": "general",
      "theoretical_price": 845.0,
      "upside_percent": 282.1
    },
    {
      "code": "6748",
      "name": "SEIWA ELECTRIC MFG CO",
      "name_jp": "星和電機",
      "website": "https://www.seiwa.co.jp",
      "market": "スタンダード",
      "score": 36,
      "valuation_score": 16,
      "growth_score": 6,
      "shareholder_score": 6,
      "quality_score_detail": 7,
      "bonus_score": 1,
      "risk_penalty": -6,
      "forecast_adj": 0,
      "net_cash_ratio": 1.32,
      "per": 7.24,
      "market_cap_oku": 88.6,
      "dividend_yield": 2.87,
      "payout_ratio": 18.93,
      "roe": 6.46,
      "roic": 9.91,
      "pbr": 0.75,
      "ai_comment": "直近四半期（2026年1Q）では売上高が前年同期比-7.2%、営業利益-39.3%、純利益-44.4%と大幅な減速が確認される。通期予想も売上260億円・営業利益19億円と前期比で横ばいから微減水準にとどまり、トレンドの悪化が鮮明。過去3期の売上は緩やかな増収を維持してきたが、足元の収益性は急速に低下している。事業面では電気機器・産業用電装部品の製造が中心で一定の技術蓄積はあるものの、顧客業界の設備投資動向に業績が左右されやすく参入障壁は限定的。PERは7倍台、PBRは0.76倍と割安感があるが、ROEは6.5%と低水準でありバリュートラップのリスクも意識される。NC比1.3倍超は財務健全性を示すが、今後の受注回復が鍵となる。",
      "risk_checks": {
        "roe_15_percent": false,
        "equity_ratio_50_percent": true,
        "debt_to_profit_5x": false,
        "fcf_stability": true,
        "liquidity_risk": false,
        "one_time_profit_risk": false
      },
      "trend_score": 2,
      "quality_score": 4,
      "chart_signals": {
        "volume_surge": false,
        "above_ma": false,
        "near_high": false
      },
      "tenbagger_stars": 2,
      "tab": "general",
      "theoretical_price": 1416.0,
      "upside_percent": 105.8
    },
    {
      "code": "4119",
      "name": "NIPPON PIGMENT HOLDINGS CO LTD",
      "name_jp": "日本ピグメントホールディングス",
      "website": "https://www.pigment.co.jp",
      "market": "スタンダード",
      "score": 35,
      "valuation_score": 16,
      "growth_score": 15,
      "shareholder_score": 9,
      "quality_score_detail": 5,
      "bonus_score": 0,
      "risk_penalty": -21,
      "forecast_adj": 0,
      "net_cash_ratio": 1.12,
      "per": 6.72,
      "market_cap_oku": 77.9,
      "dividend_yield": 1.98,
      "payout_ratio": 13.54,
      "roe": 25.42,
      "roic": 0.95,
      "pbr": 0.35,
      "ai_comment": "NIPPON PIGMENT HOLDINGSは顔料・塗料関連の素材メーカー。直近本決算では売上高+11.3%増収、営業利益は前年比+757.4%と大幅回復を示しており、業績改善が鮮明。ただし純利益は-76.9%と大幅減益で、前期に特別利益（純利益50.3億円）が発生していたとみられ一時的利益の影響が大きい。PBR0.35倍と割安感が強く、ROE25.42%は高水準。一方、営業利益率は依然薄く収益基盤は脆弱。基礎素材セクターゆえ景気・原材料価格の影響を受けやすく参入障壁も高くない。NC比1.12はネットキャッシュ水準でバランスシートは比較的健全。純利益の大幅変動は一時利益要因が主因とみられ、実力ベースの収益力の見極めが重要。",
      "risk_checks": {
        "roe_15_percent": true,
        "equity_ratio_50_percent": false,
        "debt_to_profit_5x": false,
        "fcf_stability": false,
        "liquidity_risk": false,
        "one_time_profit_risk": true
      },
      "trend_score": 7,
      "quality_score": 4,
      "chart_signals": {
        "volume_surge": false,
        "above_ma": false,
        "near_high": false
      },
      "tenbagger_stars": 3,
      "tab": "general",
      "theoretical_price": 19190.0,
      "upside_percent": 286.5
    },
    {
      "code": "4625",
      "name": "ATOMIX CO LTD",
      "name_jp": "アトミクス",
      "website": "https://www.atomix.co.jp",
      "market": "スタンダード",
      "score": 33,
      "valuation_score": 18,
      "growth_score": 6,
      "shareholder_score": 9,
      "quality_score_detail": 0,
      "bonus_score": 2,
      "risk_penalty": -13,
      "forecast_adj": 0,
      "net_cash_ratio": 1.18,
      "per": 3.96,
      "market_cap_oku": 37.4,
      "dividend_yield": 2.87,
      "payout_ratio": 11.26,
      "roe": 2.21,
      "roic": 4.66,
      "pbr": 0.33,
      "ai_comment": "ATOMIXは売上が3期連続で増収（113.9→121.2→123.5億円）と安定した成長を示しており、最新四半期（2026年3月期）では売上+3.4%・営業利益+62.6%・純利益+314.5%と大幅な利益改善が確認される。ただし年次ベースでは営業利益が前年比-2.6%と微減であり、収益性の安定には課題が残る。PBRは0.33倍と極めて割安圏にあるが、ROE2.21%と低水準で資本効率の改善が急務。塗料・建材系素材メーカーとして参入障壁は平均的。直近四半期の急回復は評価材料だが、継続性を見極める必要がある。",
      "risk_checks": {
        "roe_15_percent": false,
        "equity_ratio_50_percent": true,
        "debt_to_profit_5x": false,
        "fcf_stability": true,
        "liquidity_risk": false,
        "one_time_profit_risk": true
      },
      "trend_score": 7,
      "quality_score": 4,
      "chart_signals": {
        "volume_surge": false,
        "above_ma": false,
        "near_high": false
      },
      "tenbagger_stars": 2,
      "tab": "general",
      "theoretical_price": 2966.0,
      "upside_percent": 321.8
    },
    {
      "code": "7219",
      "name": "HKS LIMITED",
      "name_jp": "エッチ・ケー・エス",
      "website": "https://www.hks-global.com",
      "market": "スタンダード",
      "score": 33,
      "valuation_score": 19,
      "growth_score": 1,
      "shareholder_score": 6,
      "quality_score_detail": 1,
      "bonus_score": 1,
      "risk_penalty": -6,
      "forecast_adj": 0,
      "net_cash_ratio": 1.52,
      "per": 7.72,
      "market_cap_oku": 32.0,
      "dividend_yield": 2.85,
      "payout_ratio": 22.2,
      "roe": 3.39,
      "roic": 4.48,
      "pbr": 0.29,
      "ai_comment": "HKS LIMITEDは自動車アフターパーツ・チューニング用品を手がけるコンシューマー向けメーカー。年次売上は3期連続で緩やかな減収傾向にあるものの、直近の第2四半期（2026年2月期）は売上前年比+4.9%、営業利益+1.8%、純利益+40.2%と明確な回復基調を示しており、業績トレンドは底打ちから反転の兆しがある。PERは約7.8倍、PBRは0.29倍と割安水準にあるが、ROEは3.39%と低く資本効率に課題が残る。ニッチな自動車チューニング市場での一定のブランド力は競争優位となるが、市場規模の限界と収益性の低さがリスク。NC比1.52は財務的に一定の安全性を示すが、流動性懸念は限定的。",
      "risk_checks": {
        "roe_15_percent": false,
        "equity_ratio_50_percent": true,
        "debt_to_profit_5x": false,
        "fcf_stability": true,
        "liquidity_risk": false,
        "one_time_profit_risk": false
      },
      "trend_score": 4,
      "quality_score": 7,
      "chart_signals": {
        "volume_surge": false,
        "above_ma": false,
        "near_high": true
      },
      "tenbagger_stars": 2,
      "tab": "general",
      "theoretical_price": 9840.0,
      "upside_percent": 335.4
    },
    {
      "code": "8165",
      "name": "SENSHUKAI CO",
      "name_jp": "千趣会",
      "website": "https://www.senshukai.co.jp",
      "market": "スタンダード",
      "score": 31,
      "valuation_score": 23,
      "growth_score": 10,
      "shareholder_score": 6,
      "quality_score_detail": 5,
      "bonus_score": 0,
      "risk_penalty": -15,
      "forecast_adj": 0,
      "net_cash_ratio": 1.57,
      "per": 1.4,
      "market_cap_oku": 55.2,
      "dividend_yield": 0.0,
      "payout_ratio": 0.0,
      "roe": 23.12,
      "roic": -25.32,
      "pbr": 0.34,
      "ai_comment": "センシュカイは通販・カタログ事業を軸とするコンシューマーシクリカル銘柄。売上は3期連続で減収（492→458→420億円）となっており、直近1Qも前年比-6.7%と減収トレンドが継続。営業利益は赤字（-25.8億円）で、1Qも-9.88億円の赤字。ただし純利益は39.4億円と黒字で、一時的利益の可能性がある。通期予想は売上450億円・営業利益2億円と小幅回復を想定するが達成には不確実性が高い。PBRは0.34倍と極めて割安だがROEは23%超と高く、資本効率は良好。競争環境はEC化進展で厳しく、カタログ通販の構造的な縮小リスクが存在する。",
      "risk_checks": {
        "roe_15_percent": true,
        "equity_ratio_50_percent": true,
        "debt_to_profit_5x": false,
        "fcf_stability": false,
        "liquidity_risk": false,
        "one_time_profit_risk": true
      },
      "trend_score": 0,
      "quality_score": 2,
      "chart_signals": {
        "volume_surge": false,
        "above_ma": false,
        "near_high": false
      },
      "tenbagger_stars": 4,
      "tab": "general",
      "theoretical_price": 1488.0,
      "upside_percent": 1160.9
    },
    {
      "code": "8147",
      "name": "TOMITA CO LTD",
      "name_jp": "トミタ",
      "website": "https://www.tomitaj.co.jp",
      "market": "スタンダード",
      "score": 31,
      "valuation_score": 14,
      "growth_score": 15,
      "shareholder_score": 7,
      "quality_score_detail": 5,
      "bonus_score": 0,
      "risk_penalty": -19,
      "forecast_adj": 0,
      "net_cash_ratio": 1.41,
      "per": 9.5,
      "market_cap_oku": 63.4,
      "dividend_yield": 2.03,
      "payout_ratio": 18.65,
      "roe": 5.29,
      "roic": 13.34,
      "pbr": 0.49,
      "ai_comment": "TOMITA CO LTDは産業財セクターの中堅企業。過去3期の売上は202→213→217億円と緩やかな増収トレンドを維持しているが、最新四半期（2026年3月期通期）では売上+5.8%と増収ながら営業利益は-12.1%と大幅減益に転じており、収益性の悪化が懸念される。ROE5.29%・PBR0.5倍と割安感はあるが、自己資本効率は低水準。PER約9.6倍は割安圏であり、バリュー株的魅力はある。競争優位性は限定的で、産業流通・商社系の事業構造と推察され差別化要因は平均的。営業利益率は3%台と薄利体質が続いており、コスト増や市況変動に対する耐性は弱い。有利子負債倍率はNC比1.39倍とやや高め。流動性リスクは低いものの、利益の安定性に課題がある。",
      "risk_checks": {
        "roe_15_percent": false,
        "equity_ratio_50_percent": false,
        "debt_to_profit_5x": false,
        "fcf_stability": false,
        "liquidity_risk": false,
        "one_time_profit_risk": false
      },
      "trend_score": 5,
      "quality_score": 4,
      "chart_signals": {
        "volume_surge": false,
        "above_ma": false,
        "near_high": false
      },
      "tenbagger_stars": 3,
      "tab": "general",
      "theoretical_price": 2920.0,
      "upside_percent": 138.9
    },
    {
      "code": "5997",
      "name": "KYORITSU AIR TECH INC",
      "name_jp": "協立エアテック",
      "website": "https://www.kak-net.co.jp",
      "market": "スタンダード",
      "score": 31,
      "valuation_score": 14,
      "growth_score": 1,
      "shareholder_score": 6,
      "quality_score_detail": 9,
      "bonus_score": 1,
      "risk_penalty": -6,
      "forecast_adj": 0,
      "net_cash_ratio": 1.02,
      "per": 8.58,
      "market_cap_oku": 39.6,
      "dividend_yield": 2.48,
      "payout_ratio": 20.92,
      "roe": 4.69,
      "roic": 10.51,
      "pbr": 0.4,
      "ai_comment": "KYORITSU AIR TECHは空調・クリーンルーム関連の産業機器メーカー。売上は119億円台で横ばい推移だが、営業利益は前期比-12.7%と減益。最新1Q（2026年1-3月）は売上-2.0%と軟調ながら、営業利益+17.5%と採算改善の兆しが見られる。PER8.6倍・PBR0.4倍と割安感は強いが、ROE4.69%と資本効率は低い。NC比1.0は健全な財務を示す。空調設備・クリーンルーム市場は半導体・医薬品需要に支えられるが、競合も多く参入障壁はやや低め。通期予想は売上118億円・営業利益6.2億円と前期並みを見込む。利益率改善が課題で中長期的な成長ドライバーの明確化が必要。",
      "risk_checks": {
        "roe_15_percent": false,
        "equity_ratio_50_percent": true,
        "debt_to_profit_5x": false,
        "fcf_stability": true,
        "liquidity_risk": false,
        "one_time_profit_risk": false
      },
      "trend_score": 2,
      "quality_score": 4,
      "chart_signals": {
        "volume_surge": false,
        "above_ma": true,
        "near_high": true
      },
      "tenbagger_stars": 2,
      "tab": "general",
      "theoretical_price": 2333.0,
      "upside_percent": 184.6
    },
    {
      "code": "6907",
      "name": "GEOMATEC CO LTD",
      "name_jp": "ジオマテック",
      "website": "https://www.geomatec.co.jp",
      "market": "スタンダード",
      "score": 31,
      "valuation_score": 16,
      "growth_score": 9,
      "shareholder_score": 3,
      "quality_score_detail": 1,
      "bonus_score": 1,
      "risk_penalty": -13,
      "forecast_adj": 0,
      "net_cash_ratio": 1.14,
      "per": 7.37,
      "market_cap_oku": 47.1,
      "dividend_yield": 0.0,
      "payout_ratio": 0.0,
      "roe": 3.96,
      "roic": 4.42,
      "pbr": 0.45,
      "ai_comment": "ジオマテックは精密部品・薄膜技術を核とするニッチテクノロジー企業。直近FYは売上60.1億円（+13.8%）・営業利益34.1億円(+5.6%)・純利益63.8億円(+77.2%)と増収増益基調を維持。過去3期売上は58.1→46.1→52.8→60.1億円と回復・拡大傾向にある。PBR0.47倍・PER7.7倍と割安感は強いが、ROE3.96%は低水準で資本効率改善が課題。NC比1.1は財務健全性を示す。薄膜・光学コーティング分野の技術参入障壁は一定水準あるが、競合圧力や設備投資負担も存在。純利益の大幅増は一時的要因の可能性もあり注視が必要。中長期では技術力を活かした受注拡大が期待されるが、ROE・収益率の継続的改善が株価評価向上の鍵となる。",
      "risk_checks": {
        "roe_15_percent": false,
        "equity_ratio_50_percent": true,
        "debt_to_profit_5x": false,
        "fcf_stability": true,
        "liquidity_risk": false,
        "one_time_profit_risk": true
      },
      "trend_score": 7,
      "quality_score": 7,
      "chart_signals": {
        "volume_surge": false,
        "above_ma": false,
        "near_high": false
      },
      "tenbagger_stars": 2,
      "tab": "general",
      "theoretical_price": 1646.0,
      "upside_percent": 176.6
    },
    {
      "code": "3583",
      "name": "AUBEX CORP",
      "name_jp": "オーベクス",
      "website": "https://www.aubex.co.jp",
      "market": "スタンダード",
      "score": 30,
      "valuation_score": 16,
      "growth_score": 14,
      "shareholder_score": 7,
      "quality_score_detail": 13,
      "bonus_score": 1,
      "risk_penalty": -27,
      "forecast_adj": 0,
      "net_cash_ratio": 1.1,
      "per": 5.61,
      "market_cap_oku": 32.1,
      "dividend_yield": 2.95,
      "payout_ratio": 16.74,
      "roe": 8.65,
      "roic": 17.71,
      "pbr": 0.44,
      "ai_comment": "AUBEX CORPは直近四半期（FY2025-26）において売上前年比-0.3%、営業利益-26.9%、純利益-1.2%と業績が大幅に悪化している。過去3期の売上推移は53.2→53.9→60.4億円と増加傾向だったが、最新期では増収トレンドが途切れ、特に営業利益の急落が懸念される。PERは5.6倍と割安感があり、PBRも0.44倍と資産価値以下での取引が続くが、ROEは8.65%と水準は低め。Consumer Cyclicalセクターは景気敏感であり、競争環境の変化やコスト増が収益を圧迫している可能性が高い。営業利益の大幅減は一時的要因か構造的問題かの見極めが必要であり、短期的なリスクは高い。",
      "risk_checks": {
        "roe_15_percent": false,
        "equity_ratio_50_percent": false,
        "debt_to_profit_5x": false,
        "fcf_stability": false,
        "liquidity_risk": false,
        "one_time_profit_risk": true
      },
      "trend_score": 2,
      "quality_score": 4,
      "chart_signals": {
        "volume_surge": false,
        "above_ma": false,
        "near_high": false
      },
      "tenbagger_stars": 3,
      "tab": "general",
      "theoretical_price": 4126.0,
      "upside_percent": 251.4
    },
    {
      "code": "6393",
      "name": "YUKEN KOGYO CO",
      "name_jp": "油研工業",
      "website": "https://www.yuken.co.jp",
      "market": "スタンダード",
      "score": 30,
      "valuation_score": 14,
      "growth_score": 14,
      "shareholder_score": 7,
      "quality_score_detail": 5,
      "bonus_score": 2,
      "risk_penalty": -18,
      "forecast_adj": 0,
      "net_cash_ratio": 1.33,
      "per": 8.58,
      "market_cap_oku": 99.8,
      "dividend_yield": 5.32,
      "payout_ratio": 64.15,
      "roe": 5.25,
      "roic": 9.89,
      "pbr": 0.43,
      "ai_comment": "ユーケン工業は産業機械・油圧機器メーカーとして、過去3期の売上は286.8→295.1→335.0億円と増収基調を維持してきたが、直近四半期（2026年3月期通期）では売上-1.9%・営業利益-10.0%・純利益-16.4%と業績が反転悪化しており、トレンドに黄信号が点灯。ROE5.25%・PBR0.42倍と割安感はあるが収益力に課題。NC比1.34は財務健全性に一定の懸念を示す。油圧機器市場は設備投資サイクルに依存し、中国・アジア需要の鈍化リスクが直撃しやすい構造。競争優位性は技術特化型だが参入障壁は中程度。PER8.5倍と割安だが業績回復の見通しが不透明であり、慎重な評価が必要。",
      "risk_checks": {
        "roe_15_percent": false,
        "equity_ratio_50_percent": false,
        "debt_to_profit_5x": true,
        "fcf_stability": false,
        "liquidity_risk": true,
        "one_time_profit_risk": false
      },
      "trend_score": 2,
      "quality_score": 4,
      "chart_signals": {
        "volume_surge": false,
        "above_ma": false,
        "near_high": false
      },
      "tenbagger_stars": 3,
      "tab": "general",
      "theoretical_price": 7635.0,
      "upside_percent": 172.0
    },
    {
      "code": "6342",
      "name": "TAIHEI MACHINERY WORKS",
      "name_jp": "太平製作所",
      "website": "https://www.taihei-ss.co.jp",
      "market": "スタンダード",
      "score": 30,
      "valuation_score": 16,
      "growth_score": 0,
      "shareholder_score": 6,
      "quality_score_detail": 13,
      "bonus_score": 2,
      "risk_penalty": -13,
      "forecast_adj": 0,
      "net_cash_ratio": 1.31,
      "per": 7.99,
      "market_cap_oku": 35.1,
      "dividend_yield": 3.62,
      "payout_ratio": 23.69,
      "roe": 8.36,
      "roic": 26.91,
      "pbr": 0.49,
      "ai_comment": "TAIHEI MACHINERY WORKSは木材・製紙機械メーカーで、直近業績は売上78.6億円（前年比-11.2%）、営業利益9.1億円（同-36.6%）と大幅な減収減益。最新四半期データでも売上-19.0%、営業利益-37.0%と悪化が継続しており、業績トレンドは明確な下降局面にある。過去3期の売上推移は64.4→88.4→78.6億円と山型を描き、ピークアウトが鮮明。PBR0.5倍・PER8.2倍と割安感はあるが、ROE8.4%はやや低位。NC比1.28は財務健全性を示すものの、受注環境の悪化と競争激化が収益を圧迫している。産業機械分野における受注変動リスクと市場縮小懸念が課題。",
      "risk_checks": {
        "roe_15_percent": false,
        "equity_ratio_50_percent": true,
        "debt_to_profit_5x": false,
        "fcf_stability": false,
        "liquidity_risk": false,
        "one_time_profit_risk": false
      },
      "trend_score": 2,
      "quality_score": 4,
      "chart_signals": {
        "volume_surge": false,
        "above_ma": false,
        "near_high": false
      },
      "tenbagger_stars": 2,
      "tab": "general",
      "theoretical_price": 7695.0,
      "upside_percent": 185.0
    },
    {
      "code": "5282",
      "name": "GEOSTR CORP",
      "name_jp": "ジオスター",
      "website": "https://www.geostr.co.jp",
      "market": "スタンダード",
      "score": 29,
      "valuation_score": 16,
      "growth_score": 8,
      "shareholder_score": 6,
      "quality_score_detail": 6,
      "bonus_score": 1,
      "risk_penalty": -19,
      "forecast_adj": 0,
      "net_cash_ratio": 1.21,
      "per": 6.35,
      "market_cap_oku": 115.5,
      "dividend_yield": 2.67,
      "payout_ratio": 21.88,
      "roe": 3.52,
      "roic": 6.69,
      "pbr": 0.46,
      "ai_comment": "GEOSTR CORPは売上が3期連続で増収（252.4→269.1→285.3億円）を達成しており、トップライン成長は安定している。しかし直近期の営業利益は前年比-15.3%と減益に転じており、収益性の低下が懸念される。最新四半期データ（2026年3月期）では売上+1.2%・営業利益+32.2%・純利益+121.8%と大幅改善が確認され、業績回復の兆しが明確である。PBR0.46倍・PER6.3倍と割安感は強いが、ROE3.52%は低水準。NC比1.21は流動性に一定の安心感を与える。BasicMaterialsセクターとして景気敏感性・資源価格変動リスクは内包するが、直近の利益改善は評価に値する。",
      "risk_checks": {
        "roe_15_percent": false,
        "equity_ratio_50_percent": false,
        "debt_to_profit_5x": true,
        "fcf_stability": false,
        "liquidity_risk": false,
        "one_time_profit_risk": true
      },
      "trend_score": 7,
      "quality_score": 4,
      "chart_signals": {
        "volume_surge": false,
        "above_ma": false,
        "near_high": false
      },
      "tenbagger_stars": 2,
      "tab": "general",
      "theoretical_price": 1079.0,
      "upside_percent": 186.2
    },
    {
      "code": "6360",
      "name": "TOKYO AUTOMATIC MACHINERY WORKS",
      "name_jp": "東京自働機械製作所",
      "website": "https://www.tam-tokyo.co.jp",
      "market": "スタンダード",
      "score": 27,
      "valuation_score": 14,
      "growth_score": 8,
      "shareholder_score": 6,
      "quality_score_detail": 14,
      "bonus_score": 0,
      "risk_penalty": -19,
      "forecast_adj": 0,
      "net_cash_ratio": 1.02,
      "per": 8.13,
      "market_cap_oku": 59.6,
      "dividend_yield": 2.35,
      "payout_ratio": 45.92,
      "roe": 12.95,
      "roic": 23.85,
      "pbr": 2.48,
      "ai_comment": "直近四半期（2025年4月〜2026年3月期）では売上高-24.8%・営業利益-57.2%・純利益-33.9%と大幅な減収減益が確認されており、業績は急速に悪化している。過去3期の売上推移も133.1→134.6→128.9億円と直近で減少に転じており、トレンドは下向き。営業利益率は改善傾向だったが最新期で大幅に崩れた。PER8.2倍・PBR2.51倍はバリュエーション面で割安感があるものの、ROEは12.95%と15%未満。産業機械メーカーとして一定の技術的参入障壁はあるが、受注変動が大きく収益安定性に課題がある。NC比1.0超はネットキャッシュがほぼゼロ水準を示しており財務余裕は限定的。業績回復の見通しが立つまで慎重な評価が必要。",
      "risk_checks": {
        "roe_15_percent": false,
        "equity_ratio_50_percent": true,
        "debt_to_profit_5x": false,
        "fcf_stability": false,
        "liquidity_risk": true,
        "one_time_profit_risk": false
      },
      "trend_score": 0,
      "quality_score": 4,
      "chart_signals": {
        "volume_surge": false,
        "above_ma": true,
        "near_high": true
      },
      "tenbagger_stars": 3,
      "tab": "general",
      "theoretical_price": 7640.0,
      "upside_percent": 79.8
    },
    {
      "code": "5603",
      "name": "KOGI CORPORATION",
      "name_jp": "虹技",
      "website": "https://www.kogi.co.jp",
      "market": "スタンダード",
      "score": 27,
      "valuation_score": 17,
      "growth_score": 11,
      "shareholder_score": 8,
      "quality_score_detail": 4,
      "bonus_score": 1,
      "risk_penalty": -20,
      "forecast_adj": 0,
      "net_cash_ratio": 1.81,
      "per": 8.26,
      "market_cap_oku": 38.9,
      "dividend_yield": 3.43,
      "payout_ratio": 34.84,
      "roe": 5.56,
      "roic": 8.21,
      "pbr": 0.25,
      "ai_comment": "KOGI CORPORATIONは産業機械・設備関連のインダストリアルセクター企業。直近四半期（2026年3月期）では売上高が前年比-2.4%、営業利益が-44.6%、純利益が-41.1%と大幅な減収減益となっており、業績トレンドは明確に悪化している。過去3期の売上推移も267.3→259.6→263.2億円と一時回復も再び軟化傾向。PBRは0.25倍と極めて割安で、PER8.3倍も低水準だが、ROE5.56%と収益性は低い。NC比1.81はネットキャッシュ比率として一定の財務健全性を示すが、営業利益の急落は事業環境の厳しさを反映。競争優位性は平均的で参入障壁も限定的。今後の受注動向や採算改善が注目点。",
      "risk_checks": {
        "roe_15_percent": false,
        "equity_ratio_50_percent": true,
        "debt_to_profit_5x": false,
        "fcf_stability": false,
        "liquidity_risk": false,
        "one_time_profit_risk": true
      },
      "trend_score": 2,
      "quality_score": 4,
      "chart_signals": {
        "volume_surge": false,
        "above_ma": false,
        "near_high": false
      },
      "tenbagger_stars": 3,
      "tab": "general",
      "theoretical_price": 3870.0,
      "upside_percent": 226.3
    },
    {
      "code": "7670",
      "name": "O-WELL CORPORATION",
      "name_jp": "オーウエル",
      "website": "https://www.owell.co.jp",
      "market": "スタンダード",
      "score": 27,
      "valuation_score": 16,
      "growth_score": 9,
      "shareholder_score": 9,
      "quality_score_detail": 4,
      "bonus_score": 2,
      "risk_penalty": -19,
      "forecast_adj": 0,
      "net_cash_ratio": 1.29,
      "per": 5.59,
      "market_cap_oku": 100.5,
      "dividend_yield": 7.01,
      "payout_ratio": 25.16,
      "roe": 8.33,
      "roic": 7.55,
      "pbr": 0.44,
      "ai_comment": "O-WELL CORPORATIONは産業財セクターの企業で、直近の業績は売上が前期比▲2.3%と減収となったものの、営業利益は前期比＋33.2%と大幅増益を達成。最新四半期データでも売上▲1.7%・営業利益＋1.8%と減収基調が続くが、収益性改善は継続している。3期売上推移は増収後に減収に転じており、トレンドは強くない。PBRは0.44倍と割安だが、ROEは8.33%と中程度。PER5.6倍と低評価で、バリュー株的性格が強い。競争優位性は平均的で収益規模も小さく、一時的利益の可能性も排除できない。総じて収益改善努力は評価できるが、成長性に課題が残る。",
      "risk_checks": {
        "roe_15_percent": false,
        "equity_ratio_50_percent": false,
        "debt_to_profit_5x": false,
        "fcf_stability": true,
        "liquidity_risk": false,
        "one_time_profit_risk": true
      },
      "trend_score": 2,
      "quality_score": 4,
      "chart_signals": {
        "volume_surge": false,
        "above_ma": false,
        "near_high": false
      },
      "tenbagger_stars": 3,
      "tab": "general",
      "theoretical_price": 3068.0,
      "upside_percent": 207.1
    },
    {
      "code": "9932",
      "name": "SUGIMOTO & CO",
      "name_jp": "杉本商事",
      "website": "https://www.sugi-net.co.jp",
      "market": "プライム",
      "score": 27,
      "valuation_score": 14,
      "growth_score": 9,
      "shareholder_score": 5,
      "quality_score_detail": 4,
      "bonus_score": 2,
      "risk_penalty": -13,
      "forecast_adj": 0,
      "net_cash_ratio": 1.08,
      "per": 9.79,
      "market_cap_oku": 200.7,
      "dividend_yield": 4.68,
      "payout_ratio": 46.04,
      "roe": 5.4,
      "roic": 8.51,
      "pbr": 0.59,
      "ai_comment": "SUGIMOTO&COは3期連続増収を達成しており売上トレンドは良好だが、最新四半期データ（FY2025/26）では売上-1.7%・営業利益-14.5%と明確な収益悪化が確認された。営業利益率は約4.2%と薄利であり、産業財セクターの卸売業として競争優位性は限定的。PBR0.59倍・PER9.7倍と割安感はあるが、ROE5.4%は低水準でNC比1.09は財務健全性を示す。直近の減収減益傾向が今後も続く場合は業績モメンタムの悪化が懸念される。収益改善のカタリストが見えにくく、投資妙味は限定的と判断する。",
      "risk_checks": {
        "roe_15_percent": false,
        "equity_ratio_50_percent": true,
        "debt_to_profit_5x": false,
        "fcf_stability": false,
        "liquidity_risk": false,
        "one_time_profit_risk": false
      },
      "trend_score": 2,
      "quality_score": 4,
      "chart_signals": {
        "volume_surge": false,
        "above_ma": false,
        "near_high": false
      },
      "tenbagger_stars": 2,
      "tab": "general",
      "theoretical_price": 2790.0,
      "upside_percent": 143.0
    },
    {
      "code": "5986",
      "name": "MOLITEC STEEL CO",
      "name_jp": "モリテック　スチール",
      "website": "https://www.molitec.co.jp",
      "market": "スタンダード",
      "score": 27,
      "valuation_score": 18,
      "growth_score": 8,
      "shareholder_score": 6,
      "quality_score_detail": 0,
      "bonus_score": 0,
      "risk_penalty": -13,
      "forecast_adj": 0,
      "net_cash_ratio": 1.24,
      "per": 4.86,
      "market_cap_oku": 50.6,
      "dividend_yield": 2.63,
      "payout_ratio": 12.89,
      "roe": 2.27,
      "roic": 3.66,
      "pbr": 0.31,
      "ai_comment": "MOLITEC STEELは鉄鋼流通業者として売上規模は500億円超を維持しているが、直近四半期（2026年3月期）では売上が前年比-4.6%と減収。一方で営業利益は+12.1%、純利益は+216.7%と収益性は改善傾向にある。過去3期の売上推移では363→507→505億円と横ばい圏に入っており、成長の勢いは鈍化。ROE2.27%と低水準で資本効率に課題あり。PBR0.31倍と市場評価は割安だが、鉄鋼流通という参入障壁が低く価格競争が激しいセクターであり、事業の質は平均的。NetCash比率1.24と財務健全性は一定程度確保されているが、収益の絶対水準が低く持続的な成長ドライバーが見えにくい。",
      "risk_checks": {
        "roe_15_percent": false,
        "equity_ratio_50_percent": true,
        "debt_to_profit_5x": false,
        "fcf_stability": true,
        "liquidity_risk": false,
        "one_time_profit_risk": true
      },
      "trend_score": 4,
      "quality_score": 4,
      "chart_signals": {
        "volume_surge": false,
        "above_ma": false,
        "near_high": true
      },
      "tenbagger_stars": 3,
      "tab": "general",
      "theoretical_price": 767.0,
      "upside_percent": 239.5
    },
    {
      "code": "7538",
      "name": "DAISUI CO LTD",
      "name_jp": "大水",
      "website": "https://www.daisui.co.jp",
      "market": "スタンダード",
      "score": 26,
      "valuation_score": 16,
      "growth_score": 15,
      "shareholder_score": 6,
      "quality_score_detail": 5,
      "bonus_score": 1,
      "risk_penalty": -26,
      "forecast_adj": 0,
      "net_cash_ratio": 1.48,
      "per": 6.61,
      "market_cap_oku": 48.4,
      "dividend_yield": 2.01,
      "payout_ratio": 13.03,
      "roe": 10.38,
      "roic": 6.91,
      "pbr": 0.38,
      "ai_comment": "大水コーポレーションは食品流通系のディフェンシブ銘柄。直近四半期（FY2026/3期）では売上高+6.5%、営業利益+32.2%と大幅改善が見られ、トレンドは好転しつつある。ただし純利益は-38.6%と大幅減益で一過性要因の可能性がある。過去3期の売上は概ね横ばいから微増傾向。PBR0.36倍・PER6.3倍と割安感は強いが、ROE10.4%は水準としては許容範囲。営業利益率が約0.8%と極めて薄く、食品卸・流通業の構造的な低マージン体質が続く。参入障壁は低く競争は激しい。NC比1.54は財務的に問題ないが、純利益の急減には注意が必要。",
      "risk_checks": {
        "roe_15_percent": false,
        "equity_ratio_50_percent": false,
        "debt_to_profit_5x": true,
        "fcf_stability": false,
        "liquidity_risk": true,
        "one_time_profit_risk": true
      },
      "trend_score": 7,
      "quality_score": 2,
      "chart_signals": {
        "volume_surge": false,
        "above_ma": false,
        "near_high": false
      },
      "tenbagger_stars": 2,
      "tab": "general",
      "theoretical_price": 1210.0,
      "upside_percent": 240.9
    },
    {
      "code": "1420",
      "name": "SANYO HOMES CORPORATION",
      "name_jp": "サンヨーホームズ",
      "website": "https://www.sanyohomes.co.jp",
      "market": "スタンダード",
      "score": 25,
      "valuation_score": 16,
      "growth_score": 6,
      "shareholder_score": 6,
      "quality_score_detail": 1,
      "bonus_score": 2,
      "risk_penalty": -19,
      "forecast_adj": 0,
      "net_cash_ratio": 1.3,
      "per": 5.14,
      "market_cap_oku": 77.4,
      "dividend_yield": 4.05,
      "payout_ratio": 20.6,
      "roe": 4.39,
      "roic": 6.42,
      "pbr": 0.45,
      "ai_comment": "サンヨーホームズは直近四半期（2026年3月期通期）で売上+10.9%、営業利益+127.9%、純利益+108.3%と大幅な増収増益を達成しており、業績トレンドは明確に改善。過去3期の売上推移も409.7→458.6→455.2（年次）から最新期は505億円規模へ拡大。住宅業界は競争が激しくROE4.39%・PBR0.44倍と割安感があるが、参入障壁は平均的。NC比1.3倍超は一定の財務リスクを示唆。PER5倍台の超割安水準は注目に値するが、住宅市況の変動リスクや金利上昇の影響には注意が必要。",
      "risk_checks": {
        "roe_15_percent": false,
        "equity_ratio_50_percent": false,
        "debt_to_profit_5x": true,
        "fcf_stability": false,
        "liquidity_risk": false,
        "one_time_profit_risk": true
      },
      "trend_score": 9,
      "quality_score": 4,
      "chart_signals": {
        "volume_surge": false,
        "above_ma": false,
        "near_high": false
      },
      "tenbagger_stars": 2,
      "tab": "general",
      "theoretical_price": 1714.0,
      "upside_percent": 174.7
    },
    {
      "code": "6964",
      "name": "SANKO CO LTD",
      "name_jp": "サンコー",
      "website": "https://www.sko.co.jp",
      "market": "スタンダード",
      "score": 25,
      "valuation_score": 17,
      "growth_score": 0,
      "shareholder_score": 6,
      "quality_score_detail": 1,
      "bonus_score": 3,
      "risk_penalty": -13,
      "forecast_adj": 0,
      "net_cash_ratio": 1.65,
      "per": 9.6,
      "market_cap_oku": 58.1,
      "dividend_yield": 6.09,
      "payout_ratio": 29.33,
      "roe": 3.65,
      "roic": 5.05,
      "pbr": 0.36,
      "ai_comment": "直近四半期（2026年3月期）では売上高+8.6%、営業利益+39.6%と大幅改善が確認され、過去の減収減益トレンドから明確に回復基調に転じている。過去3期の売上推移は156.7→169.4→168.4億円とほぼ横ばいだったが、最新期で182.9億円へ拡大。PBR0.35倍と資産価値に対して株価は割安圏にある一方、ROE3.65%と資本効率は低水準。テクノロジーセクターながら競争優位性は平均的で、収益基盤の安定性に課題が残る。営業利益率も約4%と薄利であり、外部環境の変化に脆弱な面がある。業績回復の継続性と収益率改善が今後の焦点となる。",
      "risk_checks": {
        "roe_15_percent": false,
        "equity_ratio_50_percent": true,
        "debt_to_profit_5x": false,
        "fcf_stability": false,
        "liquidity_risk": false,
        "one_time_profit_risk": false
      },
      "trend_score": 7,
      "quality_score": 4,
      "chart_signals": {
        "volume_surge": false,
        "above_ma": false,
        "near_high": true
      },
      "tenbagger_stars": 2,
      "tab": "general",
      "theoretical_price": 2331.0,
      "upside_percent": 255.9
    },
    {
      "code": "4629",
      "name": "DAISHIN CHEMICAL",
      "name_jp": "大伸化学",
      "website": "https://www.daishin-chemical.co.jp",
      "market": "スタンダード",
      "score": 23,
      "valuation_score": 14,
      "growth_score": 3,
      "shareholder_score": 9,
      "quality_score_detail": 3,
      "bonus_score": 1,
      "risk_penalty": -18,
      "forecast_adj": 0,
      "net_cash_ratio": 1.4,
      "per": 9.4,
      "market_cap_oku": 83.6,
      "dividend_yield": 2.42,
      "payout_ratio": 23.15,
      "roe": 3.56,
      "roic": 8.51,
      "pbr": 0.48,
      "ai_comment": "DAISHIN CHEMICALは直近四半期（FY2026/3期）で売上がほぼ横ばい（-0.3%）ながら、営業利益+46.4%・純利益+51.2%と収益性が大幅改善。過去3期の売上推移は343.9→324.6→347.1億円と一時落ち込みがあり安定感に欠けるが、直近は増益基調に転換。PBR0.48倍・PER9.5倍と割安感が強く、ROE3.56%は低水準。化学素材セクターは参入障壁が中程度で競争は激しいが、一定の顧客基盤を保持。財務的には自己資本比率・有利子負債水準に注意が必要。配当・株主還元余力は限定的とみられ、成長の持続性を見極める必要がある。",
      "risk_checks": {
        "roe_15_percent": false,
        "equity_ratio_50_percent": false,
        "debt_to_profit_5x": true,
        "fcf_stability": false,
        "liquidity_risk": true,
        "one_time_profit_risk": false
      },
      "trend_score": 7,
      "quality_score": 4,
      "chart_signals": {
        "volume_surge": false,
        "above_ma": false,
        "near_high": false
      },
      "tenbagger_stars": 2,
      "tab": "general",
      "theoretical_price": 4442.0,
      "upside_percent": 143.1
    },
    {
      "code": "7218",
      "name": "TANAKA SEIMITSU KOGYO",
      "name_jp": "田中精密工業",
      "website": "https://www.tanasei.co.jp",
      "market": "スタンダード",
      "score": 21,
      "valuation_score": 16,
      "growth_score": 0,
      "shareholder_score": 6,
      "quality_score_detail": 11,
      "bonus_score": 2,
      "risk_penalty": -20,
      "forecast_adj": 0,
      "net_cash_ratio": 1.24,
      "per": 7.55,
      "market_cap_oku": 90.6,
      "dividend_yield": 3.64,
      "payout_ratio": 26.01,
      "roe": 7.44,
      "roic": 18.39,
      "pbr": 0.35,
      "ai_comment": "田中精密工業は直近四半期（2026年3月期）で売上+8.2%と増収に転じたものの、営業利益-12.3%・純利益-33.2%と収益性の悪化が深刻。過去3期売上は342→425→404億円と直近は減収、営業利益も-26.2%減と業績トレンドは弱い。二輪・自動車部品向け精密部品メーカーとして一定の技術力を持つが、競争環境は厳しくPBR0.35倍・PER7.6倍と市場評価は低い。ROE7.44%は15%を大きく下回り資本効率に課題。NC比1.24と財務的には比較的健全だが、収益の持続性に懸念が残る。EV化など構造変化への対応が中長期の焦点。",
      "risk_checks": {
        "roe_15_percent": false,
        "equity_ratio_50_percent": true,
        "debt_to_profit_5x": false,
        "fcf_stability": false,
        "liquidity_risk": false,
        "one_time_profit_risk": true
      },
      "trend_score": 2,
      "quality_score": 4,
      "chart_signals": {
        "volume_surge": false,
        "above_ma": false,
        "near_high": false
      },
      "tenbagger_stars": 2,
      "tab": "general",
      "theoretical_price": 3021.0,
      "upside_percent": 225.2
    },
    {
      "code": "2788",
      "name": "APPLE INTERNATIONAL CO LTD",
      "name_jp": "アップルインターナショナル",
      "website": "https://www.apple-international.com",
      "market": "スタンダード",
      "score": 20,
      "valuation_score": 19,
      "growth_score": 0,
      "shareholder_score": 9,
      "quality_score_detail": 2,
      "bonus_score": 1,
      "risk_penalty": -19,
      "forecast_adj": 0,
      "net_cash_ratio": 1.98,
      "per": 5.94,
      "market_cap_oku": 46.9,
      "dividend_yield": 2.73,
      "payout_ratio": 16.37,
      "roe": 7.67,
      "roic": 7.64,
      "pbr": 0.44,
      "ai_comment": "APPLE INTERNATIONAL CO LTDは直近年次では売上-6.8%・営業利益-58.7%と大幅減収減益となり業績トレンドは弱い。ただし最新1Q（2026年1-3月）ではYoY売上+36.1%・営業利益+166.4%・純利益+365.0%と急回復が確認され、通期予想も開示済み。Consumer Cyclicalセクターで競争が激しく事業の質は平均的。PBR0.44倍・PER5.9倍と割安感はあるが、ROE7.67%は15%に届かず、NC比1.99は流動性に一定の余裕。1Qの急回復がトレンド転換を示唆する点は注目だが、通期予想対比での進捗や利益率の低さは引き続き懸念材料。",
      "risk_checks": {
        "roe_15_percent": false,
        "equity_ratio_50_percent": false,
        "debt_to_profit_5x": true,
        "fcf_stability": false,
        "liquidity_risk": false,
        "one_time_profit_risk": true
      },
      "trend_score": 5,
      "quality_score": 3,
      "chart_signals": {
        "volume_surge": false,
        "above_ma": true,
        "near_high": true
      },
      "tenbagger_stars": 2,
      "tab": "general",
      "theoretical_price": 931.0,
      "upside_percent": 156.4
    },
    {
      "code": "3895",
      "name": "HAVIX CORP",
      "name_jp": "ハビックス",
      "website": "https://www.havix.co.jp",
      "market": "スタンダード",
      "score": 19,
      "valuation_score": 16,
      "growth_score": 6,
      "shareholder_score": 6,
      "quality_score_detail": 10,
      "bonus_score": 2,
      "risk_penalty": -27,
      "forecast_adj": 0,
      "net_cash_ratio": 1.05,
      "per": 5.93,
      "market_cap_oku": 32.4,
      "dividend_yield": 3.86,
      "payout_ratio": 22.89,
      "roe": 9.26,
      "roic": 11.7,
      "pbr": 0.45,
      "ai_comment": "HAVIX CORPは過去3期で売上が120.8→132.0→134.0億円と増収基調を維持しているが、直近四半期（2026年3月期）では売上が前年比▲9.6%、営業利益▲38.4%と大幅に悪化しており、業績トレンドは明確に下向きに転じている。PERは5.9倍、PBRは0.44倍と割安感はあるが、ROEは9.26%と15%を下回り、資本効率も平均的。素材セクターとして参入障壁は一定存在するものの、競争環境の激化や原材料コスト変動リスクが収益を圧迫している。NCR1.06は流動性に問題はないが、直近の収益急減が続く場合は財務余力の低下が懸念される。業績回復の兆しが確認されるまで慎重なスタンスが適切。",
      "risk_checks": {
        "roe_15_percent": false,
        "equity_ratio_50_percent": false,
        "debt_to_profit_5x": false,
        "fcf_stability": false,
        "liquidity_risk": false,
        "one_time_profit_risk": true
      },
      "trend_score": 2,
      "quality_score": 4,
      "chart_signals": {
        "volume_surge": false,
        "above_ma": false,
        "near_high": true
      },
      "tenbagger_stars": 2,
      "tab": "general",
      "theoretical_price": 1416.0,
      "upside_percent": 241.1
    },
    {
      "code": "5921",
      "name": "KAWAGISHI BRIDGE WORKS CO LTD",
      "name_jp": "川岸工業",
      "website": "https://kawagishi.co.jp",
      "market": "スタンダード",
      "score": 18,
      "valuation_score": 17,
      "growth_score": 0,
      "shareholder_score": 8,
      "quality_score_detail": 7,
      "bonus_score": 0,
      "risk_penalty": -20,
      "forecast_adj": 0,
      "net_cash_ratio": 1.92,
      "per": 9.72,
      "market_cap_oku": 110.4,
      "dividend_yield": 2.22,
      "payout_ratio": 38.78,
      "roe": 5.0,
      "roic": 7.27,
      "pbr": 0.37,
      "ai_comment": "川岐橋梁は直近年次では売上が242億円と前期比▲12.1%の減収となったが、営業利益は前期比+12.2%と増益を確保しており、コスト管理の改善が見られる。しかし直近2Q四半期データでは営業利益が前年同期比▲49.2%、純利益▲44.4%と大幅悪化しており、通期予想も営業利益10億円と年次実績18.7億円から大きく下振れが見込まれる。橋梁建設は公共インフラ需要に支えられるが競争が激しく参入障壁は限定的。PBR0.38倍と割安感があるものの、ROE5%と資本効率は低く、NC比1.9倍は財務健全性をある程度示す。直近四半期の急激な収益悪化は要注意であり、業績の先行きは不透明感が強い。",
      "risk_checks": {
        "roe_15_percent": false,
        "equity_ratio_50_percent": true,
        "debt_to_profit_5x": false,
        "fcf_stability": false,
        "liquidity_risk": false,
        "one_time_profit_risk": true
      },
      "trend_score": 2,
      "quality_score": 4,
      "chart_signals": {
        "volume_surge": false,
        "above_ma": false,
        "near_high": false
      },
      "tenbagger_stars": 2,
      "tab": "general",
      "theoretical_price": 13690.0,
      "upside_percent": 241.4
    },
    {
      "code": "7229",
      "name": "YUTAKA GIKEN CO",
      "name_jp": "ユタカ技研",
      "website": "https://www.yutakagiken.co.jp",
      "market": "スタンダード",
      "score": 16,
      "valuation_score": 16,
      "growth_score": 0,
      "shareholder_score": 3,
      "quality_score_detail": 5,
      "bonus_score": 1,
      "risk_penalty": -13,
      "forecast_adj": 0,
      "net_cash_ratio": 1.38,
      "per": 7.98,
      "market_cap_oku": 445.3,
      "dividend_yield": 2.4,
      "payout_ratio": 0.0,
      "roe": 4.45,
      "roic": 10.69,
      "pbr": 0.41,
      "ai_comment": "ユタカ技研は自動車部品（排気系・熱交換器）メーカーで、ホンダ系列に依存度が高い。過去3期売上は2180→2163→1792億円と減収トレンドが継続し、直近期の売上前年比−17.1%・営業利益−42.9%は深刻な落込み。最新四半期（FY2026/3期）では売上−4.1%と減収継続も、営業利益+1.0%・純利益+22.7%と収益面でやや回復の兆し。PBR0.41倍・PER約8倍と割安感はあるが、ROE4.45%と資本効率は低い。EV化による内燃機関関連部品の需要減退リスクが中長期的に構造的課題。競争環境は厳しく、ホンダへの依存集中リスクも残る。",
      "risk_checks": {
        "roe_15_percent": false,
        "equity_ratio_50_percent": true,
        "debt_to_profit_5x": false,
        "fcf_stability": false,
        "liquidity_risk": false,
        "one_time_profit_risk": false
      },
      "trend_score": 2,
      "quality_score": 2,
      "chart_signals": {
        "volume_surge": false,
        "above_ma": true,
        "near_high": true
      },
      "tenbagger_stars": 1,
      "tab": "general",
      "theoretical_price": 8590.0,
      "upside_percent": 185.9
    },
    {
      "code": "7427",
      "name": "ECHO TRADING CO",
      "name_jp": "エコートレーディング",
      "website": "https://echotd.co.jp",
      "market": "スタンダード",
      "score": 14,
      "valuation_score": 22,
      "growth_score": 0,
      "shareholder_score": 9,
      "quality_score_detail": 6,
      "bonus_score": 1,
      "risk_penalty": -26,
      "forecast_adj": 0,
      "net_cash_ratio": 2.11,
      "per": 6.36,
      "market_cap_oku": 49.7,
      "dividend_yield": 3.67,
      "payout_ratio": 23.32,
      "roe": 6.39,
      "roic": 18.66,
      "pbr": 0.41,
      "ai_comment": "ECHO TRADING COは3期連続で売上が緩やかに減少（1074→1064→1058億円）しており、直近期は売上前年比-0.5%、営業利益前年比-18.3%、純利益前年比-22.3%と収益性の悪化が顕著。Consumer Defensiveセクターに属するが、競争環境の激化や価格競争が利益を圧迫していると推察される。PBR0.41倍・PER6.4倍と割安感はあるが、ROE6.39%と収益性は低く、NC比2.09は財務安定性に一定の余裕を示す。営業利益率は約1.05%と極めて薄利であり、事業の質・競争優位性に乏しい。今後の収益改善に向けたコスト削減や付加価値向上が課題。上方修正の気配はなく、業績モメンタムは弱い。",
      "risk_checks": {
        "roe_15_percent": false,
        "equity_ratio_50_percent": false,
        "debt_to_profit_5x": false,
        "fcf_stability": false,
        "liquidity_risk": true,
        "one_time_profit_risk": false
      },
      "trend_score": 0,
      "quality_score": 2,
      "chart_signals": {
        "volume_surge": false,
        "above_ma": false,
        "near_high": false
      },
      "tenbagger_stars": 2,
      "tab": "general",
      "theoretical_price": 2129.0,
      "upside_percent": 160.3
    },
    {
      "code": "3320",
      "name": "CROSS PLUS INC",
      "name_jp": "クロスプラス",
      "website": "https://www.crossplus.co.jp",
      "market": "スタンダード",
      "score": 14,
      "valuation_score": 16,
      "growth_score": 5,
      "shareholder_score": 9,
      "quality_score_detail": 6,
      "bonus_score": 1,
      "risk_penalty": -27,
      "forecast_adj": 0,
      "net_cash_ratio": 1.31,
      "per": 5.55,
      "market_cap_oku": 97.1,
      "dividend_yield": 4.57,
      "payout_ratio": 21.25,
      "roe": 9.03,
      "roic": 8.54,
      "pbr": 0.5,
      "ai_comment": "CROSS PLUS INCは売上が601.9→620.0→598.5億円と直近期に減収となったが、営業利益は前期比+35.4%と大幅増益を達成。コスト管理や収益構造改善が奏功した形だが、トップラインの縮小傾向は懸念材料。アパレル・ファッション関連の消費財セクターとして競争環境は厳しく、参入障壁は低め。PER5.5倍・PBR0.5倍と割安感はあるものの、ROE9%はやや物足りない。NC比1.31は財務健全性をある程度示す。減収継続リスクや業界の構造的な競争激化を踏まえると、業績の持続性には注視が必要。短期的な利益改善は評価できるが、長期的な成長戦略の明確化が課題。",
      "risk_checks": {
        "roe_15_percent": false,
        "equity_ratio_50_percent": false,
        "debt_to_profit_5x": false,
        "fcf_stability": false,
        "liquidity_risk": false,
        "one_time_profit_risk": true
      },
      "trend_score": 2,
      "quality_score": 2,
      "chart_signals": {
        "volume_surge": false,
        "above_ma": false,
        "near_high": false
      },
      "tenbagger_stars": 2,
      "tab": "general",
      "theoretical_price": 4355.0,
      "upside_percent": 233.2
    }
  ]
}