{
  "updated_at": "2026-05-08T01:48:46+09:00",
  "stocks": [
    {
      "code": "8152",
      "name": "SOMAR CORPORATION",
      "name_jp": "ソマール",
      "website": "https://www.somar.co.jp",
      "market": "スタンダード",
      "score": 64,
      "valuation_score": 18,
      "growth_score": 19,
      "shareholder_score": 9,
      "quality_score_detail": 12,
      "bonus_score": 0,
      "risk_penalty": -6,
      "forecast_adj": 0,
      "net_cash_ratio": 1.26,
      "per": 4.83,
      "market_cap_oku": 108.3,
      "dividend_yield": 1.81,
      "payout_ratio": 8.63,
      "roe": 12.82,
      "roic": 21.08,
      "pbr": 0.5,
      "ai_comment": "SOMARコーポレーションは過去3期で売上が250.6→266.5→303.6億円と着実に拡大し、営業利益も43.0%増と大幅改善を示した。しかし最新四半期（2025年3Q）では売上前年比+1.3%とほぼ横ばいとなり、営業利益▲4.1%・純利益▲33.1%と急速に利益が悪化している。通期予想も営業利益25.8億円と保守的水準。PER4.8倍・PBR0.5倍と割安感はあるが、ROE12.8%はまずまず。NC比1.26は財務安全性に一定の余裕。ニッチな機能材料メーカーとして一定の競争優位を持つが、直近の収益失速が懸念材料。短期的な業績モメンタムの低下を考慮し慎重な姿勢が必要。\n\n【IR審査】2025年3月期決算では増収増益となったものの、草加事業所のコーティング製品事業用資産について減損損失29,089千円を特別損失に計上。売上高は303億6351万円（+13.93%）、親会社株主に帰属する当期純利益は25億8659万円（+88.66%）となった。筆頭株主はナガツタコーポレーションが18.75%保有。",
      "risk_checks": {
        "roe_15_percent": false,
        "equity_ratio_50_percent": true,
        "debt_to_profit_5x": true,
        "fcf_stability": true,
        "liquidity_risk": false,
        "one_time_profit_risk": true
      },
      "trend_score": 7,
      "quality_score": 7,
      "chart_signals": {
        "volume_surge": false,
        "above_ma": false,
        "near_high": false
      },
      "tenbagger_stars": 4,
      "tab": "general",
      "theoretical_price": 22783.0,
      "upside_percent": 307.6,
      "_source": "general",
      "score_before_ir": 66,
      "badges": [],
      "ir_review_status": "neutral",
      "ir_review_note": "業績は好調だが減損損失計上により一過性の要因あり。株価に影響を与える重要な株主還元策は確認されず。",
      "ir_reviewed_at": "2026-04-30"
    },
    {
      "code": "6743",
      "name": "DAIDO SIGNAL CO",
      "name_jp": "大同信号",
      "website": "https://www.daido-signal.co.jp",
      "market": "スタンダード",
      "score": 62,
      "valuation_score": 14,
      "growth_score": 13,
      "shareholder_score": 6,
      "quality_score_detail": 5,
      "bonus_score": 1,
      "risk_penalty": -2,
      "forecast_adj": 1,
      "net_cash_ratio": 1.15,
      "per": 8.86,
      "market_cap_oku": 131.2,
      "dividend_yield": 3.14,
      "payout_ratio": 16.08,
      "roe": 6.35,
      "roic": 5.36,
      "pbr": 0.5,
      "ai_comment": "大同信号は鉄道信号・交通インフラ分野に特化した企業で、公共インフラ向けの安定受注基盤を持つ。売上は3期連続増収トレンドを維持し、直近3Q(2025年12月期)では売上+11.7%、営業利益+42.7%と大幅改善が見られ、通期予想(売上244億円・営業利益18億円)に向けて順調に進捗している。一方、年次ベースでは営業利益が前期比-11.1%と減益であり、収益性の安定には課題が残る。ROE6.35%はやや低水準でPBR0.5倍と割安感が強いが、資本効率改善が課題。NC比1.15は財務健全性を示す。鉄道・信号分野は参入障壁が高く競合が限られるが、公共事業依存によるプロジェクト集中リスクや人件費上昇リスクに注意が必要。直近四半期の業績回復は評価でき、下期への期待が高まる局面。\n\n【IR審査】<cite index=\"2-1,11-1,12-1,15-2,20-1,21-2,33-2,34-3,34-4\">大同信号は2024年5月に179万株（12億4500万円上限）の自社株買いを実施し、8億525万円を取得。2025年5月と11月に2回連続増配を発表、配当予想を15円に上方修正。2025年6月にPBR改善を目指すPLAN2026を策定し、業績連動株主還元と政策保有株式縮減を実施。ROE向上とPBR1倍達成を目標とする資本効率改善施策を推進中。</cite>",
      "risk_checks": {
        "roe_15_percent": false,
        "equity_ratio_50_percent": true,
        "debt_to_profit_5x": true,
        "fcf_stability": true,
        "liquidity_risk": false,
        "one_time_profit_risk": false
      },
      "trend_score": 7,
      "quality_score": 7,
      "chart_signals": {
        "volume_surge": false,
        "above_ma": true,
        "near_high": false
      },
      "tenbagger_stars": 2,
      "tab": "general",
      "theoretical_price": 2006.0,
      "upside_percent": 142.6,
      "_source": "general",
      "score_before_ir": 52,
      "badges": [],
      "ir_review_status": "positive",
      "ir_review_note": "<cite index=\"2-1,11-1,12-1,15-2\">複数のカタリストが揃う。自社株買い実施・2回の増配・上方修正・PBR改善施策により株主還元強化が鮮明。</cite>",
      "ir_reviewed_at": "2026-04-30"
    },
    {
      "code": "8135",
      "name": "ZETT CORPORATION",
      "name_jp": "ゼット",
      "website": "https://zett.jp",
      "market": "スタンダード",
      "score": 60,
      "valuation_score": 20,
      "growth_score": 13,
      "shareholder_score": 9,
      "quality_score_detail": 10,
      "bonus_score": 2,
      "risk_penalty": -7,
      "forecast_adj": 0,
      "net_cash_ratio": 1.27,
      "per": 2.88,
      "market_cap_oku": 84.0,
      "dividend_yield": 4.24,
      "payout_ratio": 6.72,
      "roe": 20.56,
      "roic": 19.64,
      "pbr": 0.56,
      "ai_comment": "ZETT CORPORATIONは野球用品を中心としたスポーツ用品メーカー。売上は3期連続増収（498.9→519.6→553.1億円）で安定した成長トレンドを示し、営業利益も22.2%増と改善傾向。直近四半期（3Q）では売上+6.6%、営業利益+12.0%と堅調だが、純利益が前年比-79.1%と大幅に落ち込んでおり一時的な特殊要因の可能性に注意が必要。PERは2.88と極めて割安で、ROE20.56%は高水準。ただし野球人口減少の構造的リスクや競合との価格競争は継続的な課題。PBR0.56倍は資産価値に対して割安感があり、短期的な純利益悪化要因の精査が重要。\n\n【IR審査】<cite index=\"5-1,35-3\">ゼット株式会社の第３四半期連結累計期間は、売上高426.15億円（前年同期比6.6％増）、営業利益7.18億円（同11.9％増）と増収増益を達成しました。主力の卸売部門が好調で、スポーツ用品市場の需要拡大を背景に成長しています。</cite><cite index=\"24-1\">ROEは上昇傾向にあり、資本効率が改善していることを示します。一般的には、PBRを中心としたバリュエーションの改善が期待されます。</cite>",
      "risk_checks": {
        "roe_15_percent": true,
        "equity_ratio_50_percent": false,
        "debt_to_profit_5x": true,
        "fcf_stability": true,
        "liquidity_risk": false,
        "one_time_profit_risk": true
      },
      "trend_score": 7,
      "quality_score": 4,
      "chart_signals": {
        "volume_surge": false,
        "above_ma": false,
        "near_high": false
      },
      "tenbagger_stars": 3,
      "tab": "general",
      "theoretical_price": 2599.0,
      "upside_percent": 505.8,
      "_source": "general",
      "score_before_ir": 58,
      "badges": [],
      "ir_review_status": "positive",
      "ir_review_note": "<cite index=\"39-2\">2月13日発表の第3四半期決算で経常利益は前年同期比9.6％増の8.8億円に伸び、通期計画の13億円に対する進捗率は68.4％に達した。</cite>業績は堅調推移だが、上方修正や株主還元強化の発表はなし。",
      "ir_reviewed_at": "2026-04-30"
    },
    {
      "code": "5697",
      "name": "SANYU CO LTD",
      "name_jp": "サンユウ",
      "website": "https://www.sanyu-cfs.co.jp",
      "market": "スタンダード",
      "score": 56,
      "valuation_score": 16,
      "growth_score": 10,
      "shareholder_score": 9,
      "quality_score_detail": 3,
      "bonus_score": 2,
      "risk_penalty": -2,
      "forecast_adj": 0,
      "net_cash_ratio": 1.35,
      "per": 7.14,
      "market_cap_oku": 40.1,
      "dividend_yield": 3.82,
      "payout_ratio": 23.7,
      "roe": 4.58,
      "roic": 9.54,
      "pbr": 0.39,
      "ai_comment": "SANYU CO LTDは基礎素材セクターの企業で、過去3期の売上は239.4→240.1→244.4億円と緩やかながら連続増収を達成。最新四半期（2025年3Q累計）では売上前年比+5.0%、営業利益+26.5%、純利益+32.9%と加速しており、業績モメンタムは改善傾向。通期予想に対する進捗も順調。ただしPBR0.39倍・ROE4.58%と資本効率は低く、営業利益率も約3%程度と薄利構造が続く。NC比1.35は財務健全性を示すが、競争環境が厳しい素材業界での収益力強化が課題。割安感はあるものの収益性の抜本改善が鍵。\n\n【IR審査】2025年2月に通期経常利益を4％増益に上方修正し、配当も2円増額を発表。第3四半期は売上高5.0％増、営業利益26.4％増と好調な業績を達成。また、資本コストや株価を意識した経営対応も公表している。",
      "risk_checks": {
        "roe_15_percent": false,
        "equity_ratio_50_percent": true,
        "debt_to_profit_5x": true,
        "fcf_stability": true,
        "liquidity_risk": false,
        "one_time_profit_risk": false
      },
      "trend_score": 7,
      "quality_score": 4,
      "chart_signals": {
        "volume_surge": false,
        "above_ma": false,
        "near_high": false
      },
      "tenbagger_stars": 2,
      "tab": "general",
      "theoretical_price": 2019.0,
      "upside_percent": 204.6,
      "_source": "general",
      "score_before_ir": 49,
      "badges": [],
      "ir_review_status": "positive",
      "ir_review_note": "業績上方修正・増配・PBR改善対応と好材料が揃っており、株主還元強化の姿勢が明確",
      "ir_reviewed_at": "2026-04-30"
    },
    {
      "code": "3388",
      "name": "MEIJI ELECTRIC INDUSTRIES CO LT",
      "name_jp": "明治電機工業",
      "website": "https://www.meijidenki.co.jp",
      "market": "プライム",
      "score": 55,
      "valuation_score": 14,
      "growth_score": 14,
      "shareholder_score": 8,
      "quality_score_detail": 5,
      "bonus_score": 1,
      "risk_penalty": -6,
      "forecast_adj": 0,
      "net_cash_ratio": 1.02,
      "per": 8.52,
      "market_cap_oku": 264.9,
      "dividend_yield": 4.28,
      "payout_ratio": 30.35,
      "roe": 7.08,
      "roic": 12.44,
      "pbr": 0.74,
      "ai_comment": "明治電機工業は3期連続増収を達成しており、直近3Qでは営業利益が前年同期比40.3%増と大幅改善。売上も+1.4%と堅調で、通期予想に対する進捗も概ね順調。電気・機械設備の専門商社として一定の顧客基盤を持つが、競争環境は厳しく参入障壁は中程度。PER8.5倍・PBR0.74倍と割安感があるが、ROE7%台と資本効率はやや低水準。NC比が1.02とほぼ均衡。利益率は低いながらも着実な成長が続いており、株主還元の向上が課題。\n\n【IR審査】2026年3月期第3四半期決算で売上高1.4%増、営業利益40.2%増と増収増益。半導体・物流関連需要が底堅く推移し、生産性向上による収益改善が奏功。通期は売上高4.9%増、営業利益13.2%増を予想し、年間配当も前期比28円増の88円へ大幅増配予定。",
      "risk_checks": {
        "roe_15_percent": false,
        "equity_ratio_50_percent": true,
        "debt_to_profit_5x": false,
        "fcf_stability": true,
        "liquidity_risk": false,
        "one_time_profit_risk": false
      },
      "trend_score": 8,
      "quality_score": 4,
      "chart_signals": {
        "volume_surge": false,
        "above_ma": false,
        "near_high": false
      },
      "tenbagger_stars": 3,
      "tab": "general",
      "theoretical_price": 4014.0,
      "upside_percent": 93.2,
      "_source": "general",
      "score_before_ir": 48,
      "badges": [
        {
          "text": "⬆️増配発表",
          "sentiment": "positive"
        },
        {
          "text": "⬆️上方修正",
          "sentiment": "positive"
        }
      ],
      "ir_review_status": "positive",
      "ir_review_note": "大幅増配（前期比+47%）と営業利益の大幅改善（Q3累計40.2%増）が株価上昇の主要カタリスト。",
      "ir_reviewed_at": "2026-04-30"
    },
    {
      "code": "7991",
      "name": "MAMIYA-OP CO LTD",
      "name_jp": "マミヤ・オーピー",
      "website": "https://www.mamiya-op.co.jp",
      "market": "スタンダード",
      "score": 52,
      "valuation_score": 16,
      "growth_score": 20,
      "shareholder_score": 8,
      "quality_score_detail": 15,
      "bonus_score": 1,
      "risk_penalty": -8,
      "forecast_adj": 0,
      "net_cash_ratio": 1.17,
      "per": 5.57,
      "market_cap_oku": 129.9,
      "dividend_yield": 4.01,
      "payout_ratio": 39.87,
      "roe": 18.79,
      "roic": 38.61,
      "pbr": 0.5,
      "ai_comment": "MAMIYA-OPは過去3期で売上が159億→274億→337億円と急拡大し、営業利益も32%増と高成長を示してきた。しかし直近3Q（2025年4〜12月）の四半期データでは売上前年比▲39.7%、営業利益▲69.1%と急激な悪化が確認される。通期予想も売上210億円・営業利益20億円と大幅な縮小見通しであり、業績トレンドは転換点を迎えている可能性が高い。PERは5.6倍、PBR0.5倍と割安感はあるがROE18.8%は高水準。ネットキャッシュ比率1.17と財務は健全だが、急減収の背景（一時的要因か構造的要因か）の見極めが不可欠。競争優位性は中程度と評価する。\n\n【IR審査】マミヤ・オーピーは<cite index=\"22-1\">2026年3月期第3四半期で売上高171億8,700万円（前年同期比39.7％減）、営業利益18億6,200万円（同69.1％減）と大幅な減収減益</cite>を発表。<cite index=\"22-1\">主力の電子機器事業で特需終息の影響を受け、通期予想も下方修正</cite>された。一方、<cite index=\"39-1\">2024年1月26日に配当方針の変更及び配当予想の修正（増配）</cite>を発表している。",
      "risk_checks": {
        "roe_15_percent": true,
        "equity_ratio_50_percent": true,
        "debt_to_profit_5x": true,
        "fcf_stability": false,
        "liquidity_risk": false,
        "one_time_profit_risk": true
      },
      "trend_score": 2,
      "quality_score": 4,
      "chart_signals": {
        "volume_surge": false,
        "above_ma": false,
        "near_high": false
      },
      "tenbagger_stars": 5,
      "tab": "general",
      "theoretical_price": 5011.0,
      "upside_percent": 298.3,
      "_source": "general",
      "score_before_ir": 58,
      "badges": [
        {
          "text": "⚠️下方修正",
          "type": "negative"
        },
        {
          "text": "⚠️一過性",
          "type": "negative"
        }
      ],
      "ir_review_status": "negative",
      "ir_review_note": "パチンコ業界向け特需の剥落により大幅な業績悪化。増配実施済みだが、今後の業績見通しに不透明感が残る。",
      "ir_reviewed_at": "2026-04-30"
    },
    {
      "code": "5363",
      "name": "TYK CORPORATION",
      "name_jp": "東京窯業",
      "website": "https://www.tyk.co.jp",
      "market": "スタンダード",
      "score": 52,
      "valuation_score": 14,
      "growth_score": 18,
      "shareholder_score": 8,
      "quality_score_detail": 11,
      "bonus_score": 2,
      "risk_penalty": -6,
      "forecast_adj": 0,
      "net_cash_ratio": 1.24,
      "per": 8.99,
      "market_cap_oku": 267.9,
      "dividend_yield": 3.57,
      "payout_ratio": 32.81,
      "roe": 7.65,
      "roic": 17.98,
      "pbr": 0.59,
      "ai_comment": "TYK CORPORATIONは耐火物メーカーとして鉄鋼・セメント・ガラス業界向けに製品を供給。年次ベースでは3期連続増収増益と好調だが、最新四半期（2025年度3Q累計）では売上+0.8%と横ばい推移、営業利益は前年同期比-23.1%と大幅減益となっており、通期予想も営業利益3,600百万円と前期比減益見通し。耐火物市場は鉄鋼生産動向に連動しやすく景気敏感性が高い。PBR0.59倍・PER9倍と割安感はあるが、ROE7.65%と資本効率は低く改善余地あり。NC比1.24と財務健全性は一定水準を確保。直近の収益悪化トレンドには注意が必要。\n\n【IR審査】<cite index=\"1-2,1-3\">直近では2024年11月14日と2025年2月14日に配当予想及び業績予想の修正を発表しています。2023年11月14日には中期経営計画（2024年度～2028年度）を策定し成長戦略を示している</cite>一方で、<cite index=\"13-4\">市場では「前期の減配をネガティブ視」</cite>されており、配当政策に不透明感があります。",
      "risk_checks": {
        "roe_15_percent": false,
        "equity_ratio_50_percent": true,
        "debt_to_profit_5x": false,
        "fcf_stability": true,
        "liquidity_risk": false,
        "one_time_profit_risk": false
      },
      "trend_score": 4,
      "quality_score": 4,
      "chart_signals": {
        "volume_surge": false,
        "above_ma": true,
        "near_high": true
      },
      "tenbagger_stars": 3,
      "tab": "general",
      "theoretical_price": 1297.0,
      "upside_percent": 115.1,
      "_source": "general",
      "score_before_ir": 55,
      "badges": [
        {
          "text": "⚠️業績懸念",
          "type": "negative"
        }
      ],
      "ir_review_status": "negative",
      "ir_review_note": "中期経営計画策定は評価材料も、減配懸念と相場での投資家心理悪化が影響",
      "ir_reviewed_at": "2026-04-30"
    },
    {
      "code": "9867",
      "name": "SOLEKIA LIMITED",
      "name_jp": "ソレキア",
      "website": "https://www.solekia.com",
      "market": "スタンダード",
      "score": 51,
      "valuation_score": 16,
      "growth_score": 15,
      "shareholder_score": 9,
      "quality_score_detail": 11,
      "bonus_score": 1,
      "risk_penalty": -18,
      "forecast_adj": 0,
      "net_cash_ratio": 1.08,
      "per": 6.49,
      "market_cap_oku": 85.4,
      "dividend_yield": 0.53,
      "payout_ratio": 3.28,
      "roe": 9.73,
      "roic": 83.7,
      "pbr": 0.7,
      "ai_comment": "SOLEKIAは3期連続で売上増収を達成しており（237.7→251.8→280.3億円）、直近3Q開示では売上前年比+15.6%、営業利益+118.8%と大幅な増益を記録。通期予想も売上291億円・営業利益19.1億円と上振れ期待が高い。PERは6.5倍と割安水準で、PBR0.7倍も解散価値以下。ROEは9.73%と中程度でROE15%超には至らず。テクノロジーセクター内での競争は激しいが、一定の顧客基盤と継続的な増収が強み。NC比1.08は流動性に若干の懸念を示唆するが致命的ではない。業績モメンタムは強く、評価見直し余地が大きい銘柄と判断できる。\n\n【IR審査】2026年3月期第2四半期は売上高140億円（前年同期比+9.8%）、営業利益9.6億円（同+56.1%）の大幅増益。IT投資需要拡大やWindows 10更新需要が寄与。通期予想は増収増益を維持。特別配当は15円から通期予想では廃止見込み。",
      "risk_checks": {
        "roe_15_percent": false,
        "equity_ratio_50_percent": false,
        "debt_to_profit_5x": false,
        "fcf_stability": true,
        "liquidity_risk": true,
        "one_time_profit_risk": false
      },
      "trend_score": 10,
      "quality_score": 7,
      "chart_signals": {
        "volume_surge": false,
        "above_ma": false,
        "near_high": false
      },
      "tenbagger_stars": 3,
      "tab": "general",
      "theoretical_price": 23054.0,
      "upside_percent": 133.3,
      "_source": "general",
      "ir_review_status": "neutral",
      "ir_review_note": "業績は堅調も、東証PBR改善要請下で株主還元強化策の具体的発表はなし。投資単位引下げ検討を表明。",
      "ir_reviewed_at": "2026-04-30"
    },
    {
      "code": "7434",
      "name": "OTAKE CORP",
      "name_jp": "オータケ",
      "website": "https://www.kk-otake.co.jp",
      "market": "スタンダード",
      "score": 49,
      "valuation_score": 16,
      "growth_score": 12,
      "shareholder_score": 9,
      "quality_score_detail": 2,
      "bonus_score": 1,
      "risk_penalty": -5,
      "forecast_adj": 0,
      "net_cash_ratio": 1.17,
      "per": 7.98,
      "market_cap_oku": 75.4,
      "dividend_yield": 2.12,
      "payout_ratio": 15.37,
      "roe": 5.56,
      "roic": 7.69,
      "pbr": 0.44,
      "ai_comment": "OTAKE CORPは3期連続増収を達成しており、直近3Qでも売上高前年同期比+8.0%、営業利益+13.1%と加速傾向にある。通期予想は売上340億円・営業利益10億円で進捗率は概ね順調。ただしIndustrialsセクターにおける競争優位性は平均的で、営業利益率は約3%と薄利体質が続く。PBR0.44倍・PER7.98倍と割安感はあるが、ROE5.56%は低水準。NC比1.17は財務健全性を示す。増収増益基調は評価できるが、収益性の抜本的改善が課題。\n\n【IR審査】2025年7月に2025年5月期決算を発表し、<cite index=\"15-1\">経常損益は1,212百万円で事前予想値1,150百万円を5.4%上回る</cite>結果となった。<cite index=\"34-1\">自己株式立会外買付取引による自己株式の取得</cite>を10月に実施したが、これは<cite index=\"29-1,35-3\">譲渡制限付株式報酬</cite>用の処分に関連するもので株主還元目的ではない。配管資材卸売業として安定した事業基盤を持つ。",
      "risk_checks": {
        "roe_15_percent": false,
        "equity_ratio_50_percent": false,
        "debt_to_profit_5x": true,
        "fcf_stability": true,
        "liquidity_risk": false,
        "one_time_profit_risk": false
      },
      "trend_score": 10,
      "quality_score": 4,
      "chart_signals": {
        "volume_surge": false,
        "above_ma": true,
        "near_high": true
      },
      "tenbagger_stars": 2,
      "tab": "general",
      "theoretical_price": 5215.0,
      "upside_percent": 171.2,
      "_source": "general",
      "ir_review_status": "neutral",
      "ir_review_note": "決算は若干の上振れを示したが、大幅な業績上方修正や株主還元強化等の明確なカタリストは確認できず",
      "ir_reviewed_at": "2026-05-04"
    },
    {
      "code": "5956",
      "name": "TOSO CO LTD",
      "name_jp": "トーソー",
      "website": "https://www.toso.co.jp",
      "market": "スタンダード",
      "score": 48,
      "valuation_score": 19,
      "growth_score": 13,
      "shareholder_score": 9,
      "quality_score_detail": 1,
      "bonus_score": 2,
      "risk_penalty": -6,
      "forecast_adj": 0,
      "net_cash_ratio": 1.8,
      "per": 7.64,
      "market_cap_oku": 54.3,
      "dividend_yield": 1.68,
      "payout_ratio": 14.32,
      "roe": 3.4,
      "roic": 6.95,
      "pbr": 0.36,
      "ai_comment": "トスコは3期連続増収を達成し、直近3Qでは営業利益が前年比+80.1%と大幅改善。インテリア製品（カーテンレール・ブラインド等）を主力とするニッチ市場での安定した需要が継続している。一方、PBR0.36倍・ROE3.4%と資本効率は低水準で、株主還元・資産活用の改善余地が大きい。競争環境は住宅関連市場の中で一定のブランド認知を持つが、参入障壁は中程度。通期予想に対して3Q時点で営業利益が計画を超過しており、上振れ期待もある。バリュエーションは割安圏だが、成長ドライバーの明確化が今後の株価再評価のカギとなろう。\n\n【IR審査】<cite index=\"13-1,13-2\">2025年3月期は売上高227億8900万円（前年同期比5.5％増）、営業利益7億4600万円（同54.5％増）の大幅増益を達成。2026年3月期は売上高235億円、営業利益6億円を見込む。</cite><cite index=\"20-4\">配当は前期11.5円から今期10円予想。</cite>",
      "risk_checks": {
        "roe_15_percent": false,
        "equity_ratio_50_percent": true,
        "debt_to_profit_5x": false,
        "fcf_stability": true,
        "liquidity_risk": false,
        "one_time_profit_risk": false
      },
      "trend_score": 7,
      "quality_score": 4,
      "chart_signals": {
        "volume_surge": false,
        "above_ma": false,
        "near_high": false
      },
      "tenbagger_stars": 2,
      "tab": "general",
      "theoretical_price": 1954.0,
      "upside_percent": 218.2,
      "_source": "general",
      "score_before_ir": 49,
      "badges": [
        {
          "badge": "⬆️上方修正",
          "type": "positive"
        },
        {
          "badge": "⚠️減配予想",
          "type": "negative"
        }
      ],
      "ir_review_status": "positive",
      "ir_review_note": "<cite index=\"13-1\">前期の大幅増益は評価されるが、来期業績・配当ともに減少予想がネガティブ要因。</cite>",
      "ir_reviewed_at": "2026-04-30"
    },
    {
      "code": "4231",
      "name": "TIGERS POLYMER CORP",
      "name_jp": "タイガースポリマー",
      "website": "https://www.tiger-poly.com",
      "market": "スタンダード",
      "score": 45,
      "valuation_score": 16,
      "growth_score": 15,
      "shareholder_score": 9,
      "quality_score_detail": 8,
      "bonus_score": 2,
      "risk_penalty": -5,
      "forecast_adj": 0,
      "net_cash_ratio": 1.33,
      "per": 5.08,
      "market_cap_oku": 195.4,
      "dividend_yield": 3.6,
      "payout_ratio": 25.39,
      "roe": 7.66,
      "roic": 11.22,
      "pbr": 0.44,
      "ai_comment": "タイガースポリマーは売上高が3期連続で増収トレンドを維持しており、直近3Q累計では前年同期比で売上+4.4%・営業利益+29.6%・純利益+47.3%と大幅に改善している。通期予想も概ね達成可能な水準にある。一方で年次ベースでは営業利益が前期比-11.3%と減益となっており、利益の不安定さは懸念材料。PBR0.44倍・PER5倍台と割安感は強いが、ROE7.66%は水準として平均的。ゴム・樹脂製品の基礎素材メーカーとして安定需要はあるが、参入障壁は中程度。自動車・産業向け依存が高くシクリカルリスクも存在する。直近四半期の回復は評価できる。\n\n【IR審査】2026年2月に自社株買いを発表したプラス材料があるものの、2025年3月期第3四半期決算は売上高352億円（前年同期比5.1%減）、営業利益19億円（同35.7%減）と減収減益。通期も減収減益予想を継続し、年間配当も34円（前期比13円減配）と大幅減配を実施している。",
      "risk_checks": {
        "roe_15_percent": false,
        "equity_ratio_50_percent": false,
        "debt_to_profit_5x": true,
        "fcf_stability": true,
        "liquidity_risk": false,
        "one_time_profit_risk": false
      },
      "trend_score": 7,
      "quality_score": 4,
      "chart_signals": {
        "volume_surge": false,
        "above_ma": false,
        "near_high": false
      },
      "tenbagger_stars": 2,
      "tab": "general",
      "theoretical_price": 3691.0,
      "upside_percent": 269.1,
      "_source": "general",
      "score_before_ir": 56,
      "badges": [],
      "ir_review_status": "negative",
      "ir_review_note": "自社株買い発表があるがリスク要因が優勢。第3四半期決算の大幅減益と減配実施が株価に重し。",
      "ir_reviewed_at": "2026-04-30"
    },
    {
      "code": "8147",
      "name": "TOMITA CO LTD",
      "name_jp": "トミタ",
      "website": "https://www.tomitaj.co.jp",
      "market": "スタンダード",
      "score": 45,
      "valuation_score": 14,
      "growth_score": 15,
      "shareholder_score": 7,
      "quality_score_detail": 5,
      "bonus_score": 0,
      "risk_penalty": -6,
      "forecast_adj": 0,
      "net_cash_ratio": 1.49,
      "per": 8.64,
      "market_cap_oku": 59.9,
      "dividend_yield": 1.8,
      "payout_ratio": 16.33,
      "roe": 5.29,
      "roic": 13.34,
      "pbr": 0.48,
      "ai_comment": "TOMITA CO LTDは産業財セクターの中堅商社。過去3期の売上は202→213→216.8億円と緩やかな増収基調を維持。直近通期では営業利益が前年比26.9%増と大幅改善を達成した。ただし最新四半期（3Q累計）では売上+0.9%に対し営業利益が-1.3%と微減に転じており、通期予想の営業利益600百万円は前期比で低水準に抑えられている点は注意が必要。PBR0.48倍・PER8.6倍と割安感は強いが、ROE5.29%は低水準。ネットキャッシュ比率が1.49と財務安全性は高い。競争優位性は限定的で収益の安定性にやや課題あり。\n\n【IR審査】<cite index='35-2,13-3'>2025年3月期第2四半期累計の連結経常利益は前年同期比23.2％減の3.7億円となり、通期計画の9億円に対する進捗率は41.6％にとどまって5年平均の50.6％も下回った</cite>。<cite index='19-1,19-2'>北米での大型案件が好調で売上を牽引したが、日本での減収が影響した</cite>。<cite index='26-1,26-2'>株主優待制度の拡充がポジティブ視された</cite>。",
      "risk_checks": {
        "roe_15_percent": false,
        "equity_ratio_50_percent": true,
        "debt_to_profit_5x": false,
        "fcf_stability": true,
        "liquidity_risk": false,
        "one_time_profit_risk": false
      },
      "trend_score": 7,
      "quality_score": 4,
      "chart_signals": {
        "volume_surge": false,
        "above_ma": false,
        "near_high": false
      },
      "tenbagger_stars": 3,
      "tab": "general",
      "theoretical_price": 2917.0,
      "upside_percent": 150.3,
      "_source": "general",
      "score_before_ir": 46,
      "ir_review_status": "neutral",
      "ir_review_note": "第2四半期業績は売上増収も利益減益で進捗が遅れている。株主優待拡充は小幅プラス要因。",
      "ir_reviewed_at": "2026-05-04"
    },
    {
      "code": "7538",
      "name": "DAISUI CO LTD",
      "name_jp": "大水",
      "website": "https://www.daisui.co.jp",
      "market": "スタンダード",
      "score": 44,
      "valuation_score": 18,
      "growth_score": 15,
      "shareholder_score": 6,
      "quality_score_detail": 5,
      "bonus_score": 1,
      "risk_penalty": -12,
      "forecast_adj": 0,
      "net_cash_ratio": 1.36,
      "per": 4.42,
      "market_cap_oku": 52.6,
      "dividend_yield": 1.55,
      "payout_ratio": 6.87,
      "roe": 10.38,
      "roic": 6.91,
      "pbr": 0.42,
      "ai_comment": "大水は食品・飲料の卸売を主とするConsumer Defensiveセクター企業。年次ベースでは売上が緩やかに増収(+0.9%)も営業利益は-18.0%と減益が続く。ただし直近3Q(2025年12月期)では売上+6.6%・営業利益+14.0%と改善傾向が明確で、通期予想を上回るペースで推移している点は評価できる。PBR0.42倍・PER4.4倍と割安感は強いが、ROE10.4%はまずまず。卸売業の性質上、競争優位性は限定的で利益率も薄い。ネットキャッシュ比率1.36倍と財務安全性は高い。通期予想は保守的で上方修正の可能性あり。\n\n【IR審査】<cite index=\"23-1\">2024年11月7日に中間決算を発表</cite>し、<cite index=\"26-2\">25年3月期の連結経常利益は前の期比17.4％減の8億2400万円、26年3月期は前期比0.7％増の8億3000万円とほぼ横ばい見通し</cite>。<cite index=\"28-1\">日水系水産卸大手で近畿7市場に拠点</cite>。<cite index=\"21-1,11-1\">直近第3四半期の経常利益進捗率113%</cite>と堅調な業績推移を示している。",
      "risk_checks": {
        "roe_15_percent": false,
        "equity_ratio_50_percent": false,
        "debt_to_profit_5x": false,
        "fcf_stability": true,
        "liquidity_risk": false,
        "one_time_profit_risk": false
      },
      "trend_score": 7,
      "quality_score": 4,
      "chart_signals": {
        "volume_surge": false,
        "above_ma": false,
        "near_high": false
      },
      "tenbagger_stars": 2,
      "tab": "general",
      "theoretical_price": 1603.0,
      "upside_percent": 315.3,
      "_source": "general",
      "ir_review_status": "neutral",
      "ir_review_note": "検索した範囲では直近半年以内の自社株買い、増配、業績修正等の重要なIR情報は確認されませんでした。業績は堅調ながら特筆すべき株価カタリストは見当たらない状況です。",
      "ir_reviewed_at": "2026-04-30"
    },
    {
      "code": "8046",
      "name": "MARUFUJI SHEET PILING CO",
      "name_jp": "丸藤シートパイル",
      "website": "https://www.mrfj.co.jp",
      "market": "スタンダード",
      "score": 42,
      "valuation_score": 14,
      "growth_score": 10,
      "shareholder_score": 9,
      "quality_score_detail": 1,
      "bonus_score": 3,
      "risk_penalty": -6,
      "forecast_adj": 0,
      "net_cash_ratio": 1.25,
      "per": 9.54,
      "market_cap_oku": 166.3,
      "dividend_yield": 3.7,
      "payout_ratio": 27.0,
      "roe": 4.96,
      "roic": 6.12,
      "pbr": 0.51,
      "ai_comment": "丸藤シートパイルは直近3Q累計で売上高+12.5%、営業利益+54.9%と大幅な増収増益を達成しており、業績モメンタムは力強い。年間予想売上400億円、営業利益18.5億円に向けて順調に進捗。ただしPBR0.51倍と割安感は強い一方、ROE4.96%は低水準で資本効率に課題がある。鋼矢板・鋼管杭専業メーカーとして一定の参入障壁を持つが、建設需要の景気感応度が高く競争も激しい。NC比1.25は安定的で財務健全性は概ね良好。今後のインフラ投資需要増が追い風となる可能性があるが、収益率の低さとROEの改善が株価再評価の鍵となる。",
      "risk_checks": {
        "roe_15_percent": false,
        "equity_ratio_50_percent": true,
        "debt_to_profit_5x": false,
        "fcf_stability": true,
        "liquidity_risk": false,
        "one_time_profit_risk": false
      },
      "trend_score": 7,
      "quality_score": 4,
      "chart_signals": {
        "volume_surge": false,
        "above_ma": false,
        "near_high": false
      },
      "tenbagger_stars": 3,
      "tab": "general",
      "theoretical_price": 2511.0,
      "upside_percent": 173.2,
      "_source": "general"
    },
    {
      "code": "5753",
      "name": "NIPPON SHINDO CO",
      "name_jp": "日本伸銅",
      "website": "https://www.nippon-shindo.co.jp",
      "market": "スタンダード",
      "score": 41,
      "valuation_score": 19,
      "growth_score": 9,
      "shareholder_score": 6,
      "quality_score_detail": 13,
      "bonus_score": 1,
      "risk_penalty": -19,
      "forecast_adj": 1,
      "net_cash_ratio": 1.65,
      "per": 7.72,
      "market_cap_oku": 55.7,
      "dividend_yield": 0.58,
      "payout_ratio": 4.45,
      "roe": 8.1,
      "roic": 15.66,
      "pbr": 1.28,
      "ai_comment": "NIPPON SHINDOは直近3Q累計で売上高+9.7%、営業利益+9.8%と増収増益基調を維持しているが、純利益が-96.5%と大幅に落ち込んでおり、特別損失や一時的要因の影響が懸念される。通期予想は売上298億円・営業利益26.3億円・純利益6.2億円と保守的な着地見通し。過去3期の売上推移は272→233→261億円と回復途上。ROE8.1%、PER7.7倍、PBR1.28倍と割安感はあるが、NC比1.6倍超はネットキャッシュが潤沢でない可能性も示唆。非鉄金属・基礎素材セクターとして市況依存度が高く競争優位性は限定的。純利益の急落リスクと一時損益リスクに注意が必要。",
      "risk_checks": {
        "roe_15_percent": false,
        "equity_ratio_50_percent": false,
        "debt_to_profit_5x": true,
        "fcf_stability": false,
        "liquidity_risk": false,
        "one_time_profit_risk": true
      },
      "trend_score": 7,
      "quality_score": 4,
      "chart_signals": {
        "volume_surge": false,
        "above_ma": false,
        "near_high": false
      },
      "tenbagger_stars": 2,
      "tab": "general",
      "theoretical_price": 5280.0,
      "upside_percent": 102.7,
      "_source": "general"
    },
    {
      "code": "6497",
      "name": "HAMAI INDUSTRIES",
      "name_jp": "ハマイ",
      "website": "https://www.hamai-net.com",
      "market": "スタンダード",
      "score": 40,
      "valuation_score": 14,
      "growth_score": 13,
      "shareholder_score": 7,
      "quality_score_detail": 9,
      "bonus_score": 2,
      "risk_penalty": -19,
      "forecast_adj": 0,
      "net_cash_ratio": 1.16,
      "per": 9.27,
      "market_cap_oku": 89.9,
      "dividend_yield": 3.39,
      "payout_ratio": 27.65,
      "roe": 5.67,
      "roic": 9.43,
      "pbr": 0.53,
      "ai_comment": "HAMAI INDUSTRIESは3期連続で売上が増加（111.3→120.9→127.2億円）し、直近期も売上+5.2%・営業利益+9.4%と堅調な成長を継続している。純利益は前期比+144.7%と大幅増益を記録しており、業績モメンタムは良好。ただしPBR0.53倍・ROE5.67%と資本効率は低水準で、PER9.3倍は割安感があるものの市場の評価は限定的。産業機械セクターにおける競争優位性は一定程度存在するが、際立った参入障壁は確認しにくい。NC比1.16は適度な財務健全性を示す。中小型株特有の流動性リスクと景気感応度の高さには注意が必要。",
      "risk_checks": {
        "roe_15_percent": false,
        "equity_ratio_50_percent": true,
        "debt_to_profit_5x": false,
        "fcf_stability": true,
        "liquidity_risk": true,
        "one_time_profit_risk": true
      },
      "trend_score": 10,
      "quality_score": 4,
      "chart_signals": {
        "volume_surge": false,
        "above_ma": false,
        "near_high": false
      },
      "tenbagger_stars": 2,
      "tab": "general",
      "theoretical_price": 3592.0,
      "upside_percent": 167.9,
      "_source": "general"
    },
    {
      "code": "6748",
      "name": "SEIWA ELECTRIC MFG CO",
      "name_jp": "星和電機",
      "website": "https://www.seiwa.co.jp",
      "market": "スタンダード",
      "score": 40,
      "valuation_score": 14,
      "growth_score": 6,
      "shareholder_score": 6,
      "quality_score_detail": 7,
      "bonus_score": 1,
      "risk_penalty": -2,
      "forecast_adj": 0,
      "net_cash_ratio": 1.15,
      "per": 8.28,
      "market_cap_oku": 101.4,
      "dividend_yield": 2.59,
      "payout_ratio": 18.93,
      "roe": 6.46,
      "roic": 9.91,
      "pbr": 0.86,
      "ai_comment": "精和電機製造は売上が3期連続で増収（237.6→252.2→253.9億円）を達成しているが、直近期の営業利益は前期比-7.0%、純利益も-8.7%と減益に転じた。増収ながら収益性が低下しており、コスト増や競争激化の影響が懸念される。PERは8.3倍と割安水準、PBRも0.86倍と資産価値を下回る評価。ROEは6.46%と低位で資本効率の改善余地が大きい。NC比1.15はネットキャッシュ超過を示し財務健全性は維持。ただし増収減益の構造が続くと収益基盤の脆弱さが顕在化するリスクがある。産業用電機部品メーカーとして一定の顧客基盤を持つが、差別化要因や参入障壁は平均的水準にとどまる。",
      "risk_checks": {
        "roe_15_percent": false,
        "equity_ratio_50_percent": true,
        "debt_to_profit_5x": true,
        "fcf_stability": true,
        "liquidity_risk": false,
        "one_time_profit_risk": false
      },
      "trend_score": 4,
      "quality_score": 4,
      "chart_signals": {
        "volume_surge": false,
        "above_ma": true,
        "near_high": false
      },
      "tenbagger_stars": 2,
      "tab": "general",
      "theoretical_price": 1416.0,
      "upside_percent": 79.9,
      "_source": "general"
    },
    {
      "code": "6797",
      "name": "NAGOYA ELECTRIC WORKS",
      "name_jp": "名古屋電機工業",
      "website": "https://www.nagoya-denki.co.jp",
      "market": "スタンダード",
      "score": 38,
      "valuation_score": 16,
      "growth_score": 10,
      "shareholder_score": 6,
      "quality_score_detail": 13,
      "bonus_score": 2,
      "risk_penalty": -13,
      "forecast_adj": 0,
      "net_cash_ratio": 1.01,
      "per": 6.64,
      "market_cap_oku": 146.6,
      "dividend_yield": 3.66,
      "payout_ratio": 22.63,
      "roe": 9.85,
      "roic": 15.33,
      "pbr": 0.65,
      "ai_comment": "名古屋電機工業は道路情報板・交通インフラ分野に強みを持つが、直近3期で売上は180→175→172億円と連続減収。最新3Q累計では営業利益が前年比▲65.2%、純利益▲37.2%と急激に悪化しており、通期予想も営業利益2250百万円と前期比大幅減益の見込み。一方で売上減少局面でも営業利益率は一定水準を維持していた過去実績があり、公共インフラ向け事業の安定性は評価できる。PERは6.6倍、PBRは0.65倍と割安水準だが、ROEは9.85%と資本効率に改善余地がある。交通インフラ系の参入障壁は一定程度あるものの、公共工事依存による受注変動リスクと直近業績の急落が懸念材料。財務健全性は維持されているとみられるが、直近四半期の利益急減を重視し保守的に評価する。",
      "risk_checks": {
        "roe_15_percent": false,
        "equity_ratio_50_percent": true,
        "debt_to_profit_5x": true,
        "fcf_stability": false,
        "liquidity_risk": false,
        "one_time_profit_risk": true
      },
      "trend_score": 0,
      "quality_score": 4,
      "chart_signals": {
        "volume_surge": false,
        "above_ma": true,
        "near_high": true
      },
      "tenbagger_stars": 3,
      "tab": "general",
      "theoretical_price": 3725.0,
      "upside_percent": 198.7,
      "_source": "general"
    },
    {
      "code": "6393",
      "name": "YUKEN KOGYO CO",
      "name_jp": "油研工業",
      "website": "https://www.yuken.co.jp",
      "market": "スタンダード",
      "score": 38,
      "valuation_score": 14,
      "growth_score": 14,
      "shareholder_score": 7,
      "quality_score_detail": 5,
      "bonus_score": 2,
      "risk_penalty": -13,
      "forecast_adj": 0,
      "net_cash_ratio": 1.25,
      "per": 9.12,
      "market_cap_oku": 106.2,
      "dividend_yield": 5.03,
      "payout_ratio": 64.15,
      "roe": 5.25,
      "roic": 9.89,
      "pbr": 0.47,
      "ai_comment": "ユーケン工業は産業用油圧機器メーカー。過去3期の売上は286.8→295.1→335.0億円と増収基調を維持し、営業利益も39.3%増と高成長を示した。ただし最新四半期（3Q累計）では売上+1.6%にとどまり、営業利益▲3.3%、純利益▲14.7%と減益に転じており、通期予想も営業利益16億円と前期比減益見通し。PBR0.47倍・PER9.1倍と割安感は強いが、ROE5.25%と資本効率は低い。NC比1.25は財務安定性に一定の懸念。油圧機器分野は工作機械・建設機械向け需要の変動に左右されやすく、競争環境も厳しい。中期的な収益回復が課題。",
      "risk_checks": {
        "roe_15_percent": false,
        "equity_ratio_50_percent": true,
        "debt_to_profit_5x": false,
        "fcf_stability": false,
        "liquidity_risk": false,
        "one_time_profit_risk": false
      },
      "trend_score": 5,
      "quality_score": 4,
      "chart_signals": {
        "volume_surge": false,
        "above_ma": false,
        "near_high": true
      },
      "tenbagger_stars": 3,
      "tab": "general",
      "theoretical_price": 7433.0,
      "upside_percent": 148.9,
      "_source": "general"
    },
    {
      "code": "3134",
      "name": "HAMEE CORP",
      "name_jp": "Ｈａｍｅｅ",
      "website": "https://hamee.co.jp",
      "market": "スタンダード",
      "score": 37,
      "valuation_score": 16,
      "growth_score": 19,
      "shareholder_score": 8,
      "quality_score_detail": 14,
      "bonus_score": 2,
      "risk_penalty": -26,
      "forecast_adj": 0,
      "net_cash_ratio": 1.06,
      "per": 7.23,
      "market_cap_oku": 66.1,
      "dividend_yield": 5.1,
      "payout_ratio": 39.39,
      "roe": 12.09,
      "roic": 42.21,
      "pbr": 0.92,
      "ai_comment": "直近四半期（3Q累計）では売上が前年比-2.4%、営業利益-58.8%、純利益-72.2%と急激な悪化が見られる。通期予想でも営業利益723百万円と前期比大幅減益となる見通しで、年次ベースの好調な売上トレンドとは乖離が生じている。スマホアクセサリー関連のEC事業は競争が激しく、収益の変動性が高い。PERは7倍台、PBRは1倍割れと割安感があるものの、収益悪化が続けば評価改善は難しい。ROEも12%と目標水準を下回り、直近の業績悪化を踏まえると慎重な評価が必要。",
      "risk_checks": {
        "roe_15_percent": false,
        "equity_ratio_50_percent": false,
        "debt_to_profit_5x": false,
        "fcf_stability": false,
        "liquidity_risk": true,
        "one_time_profit_risk": false
      },
      "trend_score": 2,
      "quality_score": 2,
      "chart_signals": {
        "volume_surge": false,
        "above_ma": false,
        "near_high": false
      },
      "tenbagger_stars": 4,
      "tab": "general",
      "theoretical_price": 1046.0,
      "upside_percent": 153.2,
      "_source": "general"
    },
    {
      "code": "3583",
      "name": "AUBEX CORP",
      "name_jp": "オーベクス",
      "website": "https://www.aubex.co.jp",
      "market": "スタンダード",
      "score": 37,
      "valuation_score": 16,
      "growth_score": 14,
      "shareholder_score": 7,
      "quality_score_detail": 13,
      "bonus_score": 1,
      "risk_penalty": -20,
      "forecast_adj": 0,
      "net_cash_ratio": 1.0,
      "per": 5.61,
      "market_cap_oku": 35.4,
      "dividend_yield": 2.72,
      "payout_ratio": 12.17,
      "roe": 8.65,
      "roic": 17.71,
      "pbr": 0.5,
      "ai_comment": "AUBEX CORPは過去3期で売上が53.2→53.9→60.4億円と緩やかな増収基調を示しており、直近年度では売上+12.0%・営業利益+50.1%と大幅な増益を達成した。しかし直近3Q累計（2025年12月期）では売上前年同期比±0%、営業利益▲29.9%と収益が急激に悪化しており、通期予想も売上62億円・営業利益7.5億円と前期実績8.4億円から大幅な減益見通しとなっている。PERは5.6倍・PBR0.5倍と割安感があるものの、ROE8.65%は平均的水準。コンシューマーシクリカルセクターで競争環境が厳しく、直近の収益悪化傾向がリスク要因。NC比約1.0と財務健全性は概ね維持されているが、利益の持続性に不透明感が漂う。",
      "risk_checks": {
        "roe_15_percent": false,
        "equity_ratio_50_percent": true,
        "debt_to_profit_5x": false,
        "fcf_stability": false,
        "liquidity_risk": false,
        "one_time_profit_risk": true
      },
      "trend_score": 2,
      "quality_score": 4,
      "chart_signals": {
        "volume_surge": false,
        "above_ma": false,
        "near_high": true
      },
      "tenbagger_stars": 3,
      "tab": "general",
      "theoretical_price": 4289.0,
      "upside_percent": 232.2,
      "_source": "general"
    },
    {
      "code": "1850",
      "name": "NANKAI TATSUMURA CONSTRUCTION C",
      "name_jp": "南海辰村建設",
      "website": "https://www.nantatsu.co.jp",
      "market": "スタンダード",
      "score": 36,
      "valuation_score": 16,
      "growth_score": 15,
      "shareholder_score": 6,
      "quality_score_detail": 8,
      "bonus_score": 0,
      "risk_penalty": -18,
      "forecast_adj": 0,
      "net_cash_ratio": 1.17,
      "per": 6.01,
      "market_cap_oku": 124.2,
      "dividend_yield": 1.89,
      "payout_ratio": 6.98,
      "roe": 9.91,
      "roic": 17.69,
      "pbr": 0.63,
      "ai_comment": "南海辰村建設は直近四半期（2026年3月期）で売上が前年比-13.5%と減収となった一方、営業利益は+19.4%、純利益は+22.1%と増益を達成。過去3期の年次売上推移は424億→436億→529億と増収基調を維持していたが、最新報告では売上が大幅に落ち込んでいる。建設業として受注の波があり収益の安定性に課題。PERは6倍台と割安、PBR0.63倍で資産価値に対して割安感があるが、ROE9.91%はやや物足りない。競争が激しい建設業界において持続的な競争優位性の確立が課題。減収傾向への転換リスクに注意が必要。",
      "risk_checks": {
        "roe_15_percent": false,
        "equity_ratio_50_percent": false,
        "debt_to_profit_5x": true,
        "fcf_stability": false,
        "liquidity_risk": true,
        "one_time_profit_risk": false
      },
      "trend_score": 5,
      "quality_score": 4,
      "chart_signals": {
        "volume_surge": false,
        "above_ma": false,
        "near_high": false
      },
      "tenbagger_stars": 3,
      "tab": "general",
      "theoretical_price": 1098.0,
      "upside_percent": 154.8,
      "_source": "general"
    },
    {
      "code": "3895",
      "name": "HAVIX CORP",
      "name_jp": "ハビックス",
      "website": "https://www.havix.co.jp",
      "market": "スタンダード",
      "score": 35,
      "valuation_score": 18,
      "growth_score": 6,
      "shareholder_score": 6,
      "quality_score_detail": 10,
      "bonus_score": 2,
      "risk_penalty": -13,
      "forecast_adj": 0,
      "net_cash_ratio": 1.05,
      "per": 4.96,
      "market_cap_oku": 32.4,
      "dividend_yield": 3.89,
      "payout_ratio": 19.12,
      "roe": 9.26,
      "roic": 11.7,
      "pbr": 0.45,
      "ai_comment": "直近3Q累計（2025年12月期）では売上高9,263億円、前年同期比▲9.1%、営業利益▲38.2%と大幅に悪化しており、通期予想も売上125億円・営業利益4億円と前期比で大きく落ち込む見通し。過去3期の売上は緩やかな増収トレンドを示していたが、最新四半期データが示す急激な業績悪化が懸念材料。PERは約5倍、PBRは0.45倍と割安感はあるが、ROEは9.26%で15%に届かず収益性は中程度。基礎素材セクターは景気敏感であり、競争優位性も限定的。FCFの安定性や有利子負債水準の確認が必要。",
      "risk_checks": {
        "roe_15_percent": false,
        "equity_ratio_50_percent": true,
        "debt_to_profit_5x": false,
        "fcf_stability": false,
        "liquidity_risk": false,
        "one_time_profit_risk": false
      },
      "trend_score": 2,
      "quality_score": 4,
      "chart_signals": {
        "volume_surge": false,
        "above_ma": false,
        "near_high": true
      },
      "tenbagger_stars": 2,
      "tab": "general",
      "theoretical_price": 1548.0,
      "upside_percent": 272.9,
      "_source": "general"
    },
    {
      "code": "8138",
      "name": "SANKYO KASEI CORP",
      "name_jp": "三京化成",
      "website": "https://www.sankyokasei-corp.co.jp",
      "market": "スタンダード",
      "score": 35,
      "valuation_score": 18,
      "growth_score": 11,
      "shareholder_score": 6,
      "quality_score_detail": 2,
      "bonus_score": 0,
      "risk_penalty": -13,
      "forecast_adj": 0,
      "net_cash_ratio": 1.5,
      "per": 4.74,
      "market_cap_oku": 39.4,
      "dividend_yield": 2.28,
      "payout_ratio": 10.27,
      "roe": 7.22,
      "roic": 6.41,
      "pbr": 0.44,
      "ai_comment": "三共化成工業（SANKYO KASEI CORP）は直近3期の売上推移が267.4→262.3→271.2億円と一旦減収後に回復し、直近期は増収増益（売上+3.4%、営業利益+21.5%）を達成。最新3Q累計でも売上+2.0%・営業利益+16.6%・純利益+123.1%と好調を維持しており、通期予想達成も視野に入る。ただしPBR0.44倍・PER4.7倍と割安感が強い一方、ROE7.22%は低水準でNCR約1.5倍は良好。プラスチック成形等の素材・加工分野は競争が激しく参入障壁はやや低い。財務的にはキャッシュリッチで流動性リスクは低いが、事業の収益基盤は薄利体質であり継続的な利益改善が課題。",
      "risk_checks": {
        "roe_15_percent": false,
        "equity_ratio_50_percent": true,
        "debt_to_profit_5x": false,
        "fcf_stability": true,
        "liquidity_risk": false,
        "one_time_profit_risk": true
      },
      "trend_score": 7,
      "quality_score": 4,
      "chart_signals": {
        "volume_surge": false,
        "above_ma": false,
        "near_high": true
      },
      "tenbagger_stars": 3,
      "tab": "general",
      "theoretical_price": 14706.0,
      "upside_percent": 235.0,
      "_source": "general"
    },
    {
      "code": "7218",
      "name": "TANAKA SEIMITSU KOGYO",
      "name_jp": "田中精密工業",
      "website": "https://www.tanasei.co.jp",
      "market": "スタンダード",
      "score": 35,
      "valuation_score": 16,
      "growth_score": 0,
      "shareholder_score": 6,
      "quality_score_detail": 11,
      "bonus_score": 2,
      "risk_penalty": -6,
      "forecast_adj": 0,
      "net_cash_ratio": 1.13,
      "per": 5.56,
      "market_cap_oku": 100.2,
      "dividend_yield": 3.12,
      "payout_ratio": 18.88,
      "roe": 7.44,
      "roic": 18.39,
      "pbr": 0.38,
      "ai_comment": "田中精密工業は直近3Qで売上+3.3%と増収基調に転じているものの、営業利益は-14.9%と大幅減益が継続している。通期予想でも営業利益2,100百万円と低水準にとどまり、収益性の回復には時間を要する見込み。PBR0.38倍・PER5.56倍と著しく割安に放置されており、NC比1.13倍でネットキャッシュ体質である点は財務的安定性を示す。ROE7.44%はROE15%基準を下回り、資本効率の改善が課題。二輪・四輪部品向け精密加工という特定市場への依存度が高く、参入障壁は中程度。Consumer Cyclical特性上、自動車需要の変動リスクに直接さらされている。減益トレンドが続く中、バリュー株としての側面はあるが業績回復の確証は乏しい。",
      "risk_checks": {
        "roe_15_percent": false,
        "equity_ratio_50_percent": true,
        "debt_to_profit_5x": false,
        "fcf_stability": true,
        "liquidity_risk": false,
        "one_time_profit_risk": false
      },
      "trend_score": 2,
      "quality_score": 4,
      "chart_signals": {
        "volume_surge": false,
        "above_ma": false,
        "near_high": false
      },
      "tenbagger_stars": 2,
      "tab": "general",
      "theoretical_price": 3480.0,
      "upside_percent": 237.5,
      "_source": "general"
    },
    {
      "code": "5984",
      "name": "KANEFUSA CORP",
      "name_jp": "兼房",
      "website": "https://www.kanefusa.co.jp",
      "market": "スタンダード",
      "score": 35,
      "valuation_score": 14,
      "growth_score": 5,
      "shareholder_score": 9,
      "quality_score_detail": 3,
      "bonus_score": 1,
      "risk_penalty": -6,
      "forecast_adj": 1,
      "net_cash_ratio": 1.16,
      "per": 8.83,
      "market_cap_oku": 109.9,
      "dividend_yield": 2.25,
      "payout_ratio": 27.92,
      "roe": 3.22,
      "roic": 2.93,
      "pbr": 0.37,
      "ai_comment": "カネフサは工業用切削工具メーカーで、一定のニッチ市場での地位を持つ。年次ベースでは売上がほぼ横ばい（211→201→202億円）で推移し、営業利益は前期比29%減と大幅減益となっている。ただし最新四半期（3Q累計）では売上+4.2%、営業利益+64.5%と急回復しており、通期予想も営業利益10億円で着地見込み。PBR0.37倍・PER8.8倍と割安感は強いが、ROE3.22%と低く資本効率に課題。NC比1.16はネットキャッシュ状況が良好なことを示し、財務安定性は高い。競争優位性は切削工具の専門性にあるが、業界全体での価格競争は継続しており、収益性の改善が鍵となる。",
      "risk_checks": {
        "roe_15_percent": false,
        "equity_ratio_50_percent": true,
        "debt_to_profit_5x": false,
        "fcf_stability": true,
        "liquidity_risk": false,
        "one_time_profit_risk": false
      },
      "trend_score": 4,
      "quality_score": 4,
      "chart_signals": {
        "volume_surge": false,
        "above_ma": false,
        "near_high": true
      },
      "tenbagger_stars": 2,
      "tab": "general",
      "theoretical_price": 2808.0,
      "upside_percent": 255.0,
      "_source": "general"
    },
    {
      "code": "7521",
      "name": "MUSASHI CO LTD",
      "name_jp": "ムサシ",
      "website": "https://www.musashinet.co.jp",
      "market": "スタンダード",
      "score": 34,
      "valuation_score": 16,
      "growth_score": 9,
      "shareholder_score": 9,
      "quality_score_detail": 12,
      "bonus_score": 0,
      "risk_penalty": -19,
      "forecast_adj": 1,
      "net_cash_ratio": 1.13,
      "per": 5.96,
      "market_cap_oku": 190.8,
      "dividend_yield": 1.28,
      "payout_ratio": 7.67,
      "roe": 10.1,
      "roic": 28.73,
      "pbr": 0.54,
      "ai_comment": "MUSASHIは直近年次では売上・営業利益ともに大幅改善（営業利益+211%）を達成したが、最新3Q四半期データでは売上▲0.5%、営業利益▲12.3%、純利益▲58.4%と急速に悪化しており、通期予想も保守的水準に留まる。産業機械・部品系の中堅メーカーとして一定の技術力を持つが、競合環境は厳しく参入障壁は中程度。PERは約6倍と割安感があるが、ROEは10%程度でPBRも0.54倍と市場評価は低め。NC比1.13はネットキャッシュがほぼ均衡水準で財務安定性は標準的。直近四半期の利益急落が構造的な収益力の低下を示している可能性があり、下期回復に向けた実績確認が必要。",
      "risk_checks": {
        "roe_15_percent": false,
        "equity_ratio_50_percent": false,
        "debt_to_profit_5x": true,
        "fcf_stability": false,
        "liquidity_risk": false,
        "one_time_profit_risk": true
      },
      "trend_score": 2,
      "quality_score": 4,
      "chart_signals": {
        "volume_surge": false,
        "above_ma": true,
        "near_high": true
      },
      "tenbagger_stars": 2,
      "tab": "general",
      "theoretical_price": 9750.0,
      "upside_percent": 248.2,
      "_source": "general"
    },
    {
      "code": "5997",
      "name": "KYORITSU AIR TECH INC",
      "name_jp": "協立エアテック",
      "website": "https://www.kak-net.co.jp",
      "market": "スタンダード",
      "score": 31,
      "valuation_score": 14,
      "growth_score": 1,
      "shareholder_score": 6,
      "quality_score_detail": 9,
      "bonus_score": 1,
      "risk_penalty": -6,
      "forecast_adj": 0,
      "net_cash_ratio": 1.02,
      "per": 8.53,
      "market_cap_oku": 39.3,
      "dividend_yield": 2.44,
      "payout_ratio": 20.92,
      "roe": 4.69,
      "roic": 10.51,
      "pbr": 0.4,
      "ai_comment": "KYORITSU AIR TECHは空調設備・クリーンルーム関連の専業メーカーで、売上は119億円前後で横ばい推移。直近期は売上が小幅増収（+1.6%）となったものの、営業利益は-12.7%と明確に減益。3期の売上推移は119→117→119と横ばい圏で成長力に乏しい。PBR0.4倍・PER8.5倍と割安水準だが、ROE4.69%と資本効率は低く改善余地が大きい。産業用空調・クリーンルームという安定需要はあるものの、競合多数で差別化は限定的。財務健全性は一定水準を維持しているとみられるが、収益性の低さと成長性の欠如が課題。半導体・製薬向け需要が追い風になるかが注目点。",
      "risk_checks": {
        "roe_15_percent": false,
        "equity_ratio_50_percent": true,
        "debt_to_profit_5x": false,
        "fcf_stability": true,
        "liquidity_risk": false,
        "one_time_profit_risk": false
      },
      "trend_score": 2,
      "quality_score": 4,
      "chart_signals": {
        "volume_surge": false,
        "above_ma": true,
        "near_high": true
      },
      "tenbagger_stars": 2,
      "tab": "general",
      "theoretical_price": 2319.0,
      "upside_percent": 184.5,
      "_source": "general"
    },
    {
      "code": "6360",
      "name": "TOKYO AUTOMATIC MACHINERY WORKS",
      "name_jp": "東京自働機械製作所",
      "website": "https://www.tam-tokyo.co.jp",
      "market": "スタンダード",
      "score": 29,
      "valuation_score": 16,
      "growth_score": 8,
      "shareholder_score": 6,
      "quality_score_detail": 14,
      "bonus_score": 0,
      "risk_penalty": -19,
      "forecast_adj": 0,
      "net_cash_ratio": 1.07,
      "per": 7.71,
      "market_cap_oku": 56.6,
      "dividend_yield": 4.0,
      "payout_ratio": 45.92,
      "roe": 12.95,
      "roic": 23.85,
      "pbr": 2.35,
      "ai_comment": "東京自動機工は直近3Qで売上前年比-43.3%、営業利益-95.0%と急激な業績悪化が確認される。通期予想も売上100億円・営業利益4億円と前期比で大幅減収減益見通しであり、年間ベースの売上推移（133→134→128億円）も直近で減少傾向。タバコ関連製造機械等のニッチ市場で一定の技術的参入障壁はあるが、顧客集中リスクや需要変動の影響を受けやすく事業の質は平均的。PERは7.7倍と割安感があるが、ROEは12.95%と15%未満。業績の急速な悪化を踏まえると短期的なリスクは高く、慎重な姿勢が必要。",
      "risk_checks": {
        "roe_15_percent": false,
        "equity_ratio_50_percent": true,
        "debt_to_profit_5x": false,
        "fcf_stability": false,
        "liquidity_risk": true,
        "one_time_profit_risk": false
      },
      "trend_score": 0,
      "quality_score": 4,
      "chart_signals": {
        "volume_surge": false,
        "above_ma": true,
        "near_high": true
      },
      "tenbagger_stars": 3,
      "tab": "general",
      "theoretical_price": 7644.0,
      "upside_percent": 89.7,
      "_source": "general"
    },
    {
      "code": "8165",
      "name": "SENSHUKAI CO",
      "name_jp": "千趣会",
      "website": "https://www.senshukai.co.jp",
      "market": "スタンダード",
      "score": 28,
      "valuation_score": 20,
      "growth_score": 10,
      "shareholder_score": 6,
      "quality_score_detail": 5,
      "bonus_score": 0,
      "risk_penalty": -15,
      "forecast_adj": 0,
      "net_cash_ratio": 1.45,
      "per": 1.52,
      "market_cap_oku": 59.9,
      "dividend_yield": 0.0,
      "payout_ratio": 0.0,
      "roe": 23.12,
      "roic": -25.32,
      "pbr": 0.35,
      "ai_comment": "千趣会（SENSHUKAI）は通販・カタログ事業を核とするコンシューマー企業。過去3期売上は492→459→421億円と一貫して減収トレンドが続き、直近1Qも前年比-6.7%・営業赤字-9.9億円と業績悪化継続。通期予想では営業利益200百万円・純利益13.5億円と黒字転換を見込むが、1Qの赤字幅を考えると達成の確度は不透明。PBR0.35倍と資産的な割安感はあり、ROE23%は高水準だが純利益に一時的要因（39.4億円）が含まれる可能性あり。EC化・競合激化でカタログ通販のビジネスモデル自体が構造的に縮小しており、競争優位性は低下傾向。財務安定性（NC比1.45）は一定程度保たれているが、売上・利益の持続的改善が見通しにくいリスクが高い。",
      "risk_checks": {
        "roe_15_percent": true,
        "equity_ratio_50_percent": true,
        "debt_to_profit_5x": false,
        "fcf_stability": false,
        "liquidity_risk": false,
        "one_time_profit_risk": true
      },
      "trend_score": 0,
      "quality_score": 2,
      "chart_signals": {
        "volume_surge": false,
        "above_ma": false,
        "near_high": false
      },
      "tenbagger_stars": 4,
      "tab": "general",
      "theoretical_price": 1504.0,
      "upside_percent": 1075.2,
      "_source": "general"
    },
    {
      "code": "7670",
      "name": "O-WELL CORPORATION",
      "name_jp": "オーウエル",
      "website": "https://www.owell.co.jp",
      "market": "スタンダード",
      "score": 28,
      "valuation_score": 16,
      "growth_score": 9,
      "shareholder_score": 9,
      "quality_score_detail": 4,
      "bonus_score": 2,
      "risk_penalty": -18,
      "forecast_adj": 0,
      "net_cash_ratio": 1.24,
      "per": 5.89,
      "market_cap_oku": 104.1,
      "dividend_yield": 4.31,
      "payout_ratio": 25.6,
      "roe": 8.33,
      "roic": 7.55,
      "pbr": 0.47,
      "ai_comment": "O-WELL CORPORATIONは産業セクターに属し、過去3期の売上推移は643.3→710.5→694.2億円と増収後に若干の減収となっている。直近3Qの売上前年比-1.7%、営業利益はほぼ横ばい(+0.0%)と業績は踊り場局面。ただし純利益は+6.6%と改善しており、通期予想も概ね維持されている。PER5.9倍・PBR0.47倍と割安感が強く、バリュー株的側面あり。ROE8.33%は中程度で改善余地がある。NC比1.24は財務健全性に一定の懸念。営業利益率が約1.8%と薄利であり、収益構造の脆弱性が課題。競合との差別化要因が不明確で競争環境は厳しいと推察される。",
      "risk_checks": {
        "roe_15_percent": false,
        "equity_ratio_50_percent": false,
        "debt_to_profit_5x": true,
        "fcf_stability": false,
        "liquidity_risk": true,
        "one_time_profit_risk": false
      },
      "trend_score": 2,
      "quality_score": 4,
      "chart_signals": {
        "volume_surge": false,
        "above_ma": false,
        "near_high": false
      },
      "tenbagger_stars": 3,
      "tab": "general",
      "theoretical_price": 3010.0,
      "upside_percent": 190.8,
      "_source": "general"
    },
    {
      "code": "7219",
      "name": "HKS LIMITED",
      "name_jp": "エッチ・ケー・エス",
      "website": "https://www.hks-global.com",
      "market": "スタンダード",
      "score": 28,
      "valuation_score": 19,
      "growth_score": 1,
      "shareholder_score": 6,
      "quality_score_detail": 1,
      "bonus_score": 1,
      "risk_penalty": -6,
      "forecast_adj": 0,
      "net_cash_ratio": 1.53,
      "per": 7.69,
      "market_cap_oku": 31.9,
      "dividend_yield": 2.88,
      "payout_ratio": 22.2,
      "roe": 3.39,
      "roic": 4.48,
      "pbr": 0.29,
      "ai_comment": "HKS LIMITEDは過去3期で売上が92.4→90.0→89.8億円と緩やかな減収トレンドが続いており、営業利益も前期比-5.5%と減益。ただし直近四半期（2Q累計）では売上+4.9%・営業利益+1.8%・純利益+40.2%と回復基調が見られ、通期予想は売上93.75億円・営業利益3.0億円を設定。PBR0.29倍・PER7.7倍と割安感は強いが、ROE3.39%と収益性は低水準。自動車チューニングパーツという特定ニッチ市場での認知度は高いが、市場規模の限界や競合圧力もあり事業規模拡大には課題がある。財務健全性は概ね良好だが、低収益体質の改善が株価再評価の鍵となる。",
      "risk_checks": {
        "roe_15_percent": false,
        "equity_ratio_50_percent": true,
        "debt_to_profit_5x": false,
        "fcf_stability": true,
        "liquidity_risk": false,
        "one_time_profit_risk": false
      },
      "trend_score": 2,
      "quality_score": 4,
      "chart_signals": {
        "volume_surge": false,
        "above_ma": false,
        "near_high": true
      },
      "tenbagger_stars": 2,
      "tab": "general",
      "theoretical_price": 9841.0,
      "upside_percent": 337.0,
      "_source": "general"
    },
    {
      "code": "5603",
      "name": "KOGI CORPORATION",
      "name_jp": "虹技",
      "website": "https://www.kogi.co.jp",
      "market": "スタンダード",
      "score": 26,
      "valuation_score": 21,
      "growth_score": 11,
      "shareholder_score": 9,
      "quality_score_detail": 4,
      "bonus_score": 1,
      "risk_penalty": -26,
      "forecast_adj": 0,
      "net_cash_ratio": 1.59,
      "per": 4.93,
      "market_cap_oku": 44.4,
      "dividend_yield": 3.77,
      "payout_ratio": 21.86,
      "roe": 5.56,
      "roic": 8.21,
      "pbr": 0.3,
      "ai_comment": "KOGI CORPORATIONは直近四半期（3Q累計）で売上が前年比-2.1%、営業利益-44.3%、純利益-43.7%と大幅な減益トレンドに転じており、通期予想も営業利益780百万円と前期比で低水準にとどまる見込みです。過去3期の売上推移は267.3→259.6→263.2億円と横ばい圏での推移であり、成長力は乏しい。PERは約4.9倍、PBR0.3倍と割安感はあるものの、ROE5.56%と資本効率は低く、収益性改善の道筋が見えにくい状況です。産業機械・設備系インフラ事業として一定の安定性はありますが、競争優位性は限定的で利益率も低い。直近の急激な収益悪化はリスク要因として重視すべきであり、上方修正の可能性も低いと判断します。",
      "risk_checks": {
        "roe_15_percent": false,
        "equity_ratio_50_percent": false,
        "debt_to_profit_5x": false,
        "fcf_stability": false,
        "liquidity_risk": true,
        "one_time_profit_risk": false
      },
      "trend_score": 2,
      "quality_score": 4,
      "chart_signals": {
        "volume_surge": false,
        "above_ma": false,
        "near_high": false
      },
      "tenbagger_stars": 3,
      "tab": "general",
      "theoretical_price": 4685.0,
      "upside_percent": 246.2,
      "_source": "general"
    },
    {
      "code": "7887",
      "name": "NANKAI PLYWOOD CO",
      "name_jp": "南海プライウッド",
      "website": "https://www.nankaiplywood.co.jp",
      "market": "スタンダード",
      "score": 26,
      "valuation_score": 16,
      "growth_score": 6,
      "shareholder_score": 6,
      "quality_score_detail": 0,
      "bonus_score": 1,
      "risk_penalty": -19,
      "forecast_adj": 2,
      "net_cash_ratio": 1.02,
      "per": 6.95,
      "market_cap_oku": 102.7,
      "dividend_yield": 1.9,
      "payout_ratio": 9.83,
      "roe": 0.41,
      "roic": 4.14,
      "pbr": 0.4,
      "ai_comment": "南海プライウッドは3期連続増収を達成し、直近四半期（3Q累計）では営業利益が前年同期比103.6%増、純利益は164.0%増と大幅改善。通期予想に対する進捗率も良好で、上振れ期待がある。売上高は緩やかに拡大しており業績トレンドは良好。一方、合板・木材関連業界は価格変動・輸入材リスク・建設需要に左右される競争環境にあり事業の質は平均的。ROEは0.41%と極めて低く資本効率に課題。PBRは0.4倍と割安感あるが改善余地は限定的。財務安定性や流動性懸念は低い水準と判断する。",
      "risk_checks": {
        "roe_15_percent": false,
        "equity_ratio_50_percent": false,
        "debt_to_profit_5x": false,
        "fcf_stability": true,
        "liquidity_risk": false,
        "one_time_profit_risk": true
      },
      "trend_score": 10,
      "quality_score": 4,
      "chart_signals": {
        "volume_surge": false,
        "above_ma": false,
        "near_high": false
      },
      "tenbagger_stars": 2,
      "tab": "general",
      "theoretical_price": 7441.0,
      "upside_percent": 251.1,
      "_source": "general"
    },
    {
      "code": "5921",
      "name": "KAWAGISHI BRIDGE WORKS CO LTD",
      "name_jp": "川岸工業",
      "website": "https://kawagishi.co.jp",
      "market": "スタンダード",
      "score": 25,
      "valuation_score": 17,
      "growth_score": 0,
      "shareholder_score": 8,
      "quality_score_detail": 7,
      "bonus_score": 0,
      "risk_penalty": -13,
      "forecast_adj": 0,
      "net_cash_ratio": 1.84,
      "per": 8.06,
      "market_cap_oku": 115.2,
      "dividend_yield": 2.15,
      "payout_ratio": 30.71,
      "roe": 5.0,
      "roic": 7.27,
      "pbr": 0.4,
      "ai_comment": "川岸工業は橋梁・鉄骨製品を手掛けるBasic Materialsセクター企業。直近年度は売上が242.2億円と前期比▲12.1%の減収ながら、営業利益は18.7億円で前期比+12.2%と増益を確保しており、コスト管理の改善が見られる。しかし最新四半期（2025年12月期1Q）では売上▲2.8%、営業利益▲112.4%と大幅悪化しており、通期予想（売上220億円・営業利益10億円）は年間業績をさらに下回る可能性を示唆する。PBR0.4倍・PER約8倍と割安感はあるものの、ROE5%は低水準。橋梁業界は公共インフラ需要に依存し参入障壁は中程度だが、受注変動リスクが大きく収益の安定性に課題がある。",
      "risk_checks": {
        "roe_15_percent": false,
        "equity_ratio_50_percent": true,
        "debt_to_profit_5x": false,
        "fcf_stability": false,
        "liquidity_risk": false,
        "one_time_profit_risk": false
      },
      "trend_score": 2,
      "quality_score": 4,
      "chart_signals": {
        "volume_surge": false,
        "above_ma": false,
        "near_high": true
      },
      "tenbagger_stars": 2,
      "tab": "general",
      "theoretical_price": 14232.0,
      "upside_percent": 238.9,
      "_source": "general"
    },
    {
      "code": "3320",
      "name": "CROSS PLUS INC",
      "name_jp": "クロスプラス",
      "website": "https://www.crossplus.co.jp",
      "market": "スタンダード",
      "score": 24,
      "valuation_score": 16,
      "growth_score": 5,
      "shareholder_score": 9,
      "quality_score_detail": 6,
      "bonus_score": 1,
      "risk_penalty": -19,
      "forecast_adj": 0,
      "net_cash_ratio": 1.3,
      "per": 5.62,
      "market_cap_oku": 98.3,
      "dividend_yield": 4.49,
      "payout_ratio": 21.25,
      "roe": 9.03,
      "roic": 8.54,
      "pbr": 0.5,
      "ai_comment": "CROSS PLUS INCは直近期で売上が前年比-3.5%と減収となったが、営業利益は+35.6%と大幅増益を達成。売上推移は601.9→620.0→598.5億円と直近は減少に転じており、トップライン成長には課題がある。一方で収益性改善は顕著でコスト構造の最適化が進んでいるとみられる。PERは5.6倍、PBRは0.5倍と割安感が強く、ROEは9%程度。アパレル・消費財分野は競争激化が続く環境であり、参入障壁は限定的。NC比1.3は流動性に問題はなく財務は安定的だが、今後の増収回帰が評価の鍵となる。",
      "risk_checks": {
        "roe_15_percent": false,
        "equity_ratio_50_percent": false,
        "debt_to_profit_5x": false,
        "fcf_stability": true,
        "liquidity_risk": false,
        "one_time_profit_risk": true
      },
      "trend_score": 2,
      "quality_score": 4,
      "chart_signals": {
        "volume_surge": false,
        "above_ma": false,
        "near_high": true
      },
      "tenbagger_stars": 2,
      "tab": "general",
      "theoretical_price": 4354.0,
      "upside_percent": 229.1,
      "_source": "general"
    },
    {
      "code": "6249",
      "name": "GAMECARD HOLDINGS INC",
      "name_jp": "ゲームカードホールディングス",
      "website": "https://www.gc-holdings.co.jp",
      "market": "スタンダード",
      "score": 23,
      "valuation_score": 19,
      "growth_score": 6,
      "shareholder_score": 6,
      "quality_score_detail": 14,
      "bonus_score": 2,
      "risk_penalty": -26,
      "forecast_adj": 0,
      "net_cash_ratio": 1.51,
      "per": 7.52,
      "market_cap_oku": 359.1,
      "dividend_yield": 3.94,
      "payout_ratio": 29.38,
      "roe": 11.24,
      "roic": 18.96,
      "pbr": 0.59,
      "ai_comment": "直近四半期（2025年3Q累計）では売上高が前年同期比-33.2%、営業利益-42.1%、純利益-47.3%と大幅な悪化が確認される。通期予想も売上280億円・営業利益50億円と年次データ（売上379.5億円・営業利益90.2億円）から大きく下振れており、業績は急速に悪化している。過去3期の売上推移は増収基調だったが、現在は明確な反転局面にある。PBR0.59倍・PER7.5倍と割安感はあるが、ROEは11.24%と15%未満。インダストリアルズセクターで競争優位性は限定的。NC比1.51はやや財務に余裕を示すが、収益急落がキャッシュフローに影響する懸念が残る。業績悪化の構造的要因の見極めが急務であり、現時点での投資は慎重姿勢が必要。",
      "risk_checks": {
        "roe_15_percent": false,
        "equity_ratio_50_percent": false,
        "debt_to_profit_5x": false,
        "fcf_stability": false,
        "liquidity_risk": true,
        "one_time_profit_risk": false
      },
      "trend_score": 0,
      "quality_score": 2,
      "chart_signals": {
        "volume_surge": false,
        "above_ma": false,
        "near_high": false
      },
      "tenbagger_stars": 1,
      "tab": "general",
      "theoretical_price": 8415.0,
      "upside_percent": 228.7,
      "_source": "general"
    },
    {
      "code": "3420",
      "name": "KFC LTD (JAPAN)",
      "name_jp": "ケー・エフ・シー",
      "website": "https://www.kfc-net.co.jp",
      "market": "スタンダード",
      "score": 23,
      "valuation_score": 14,
      "growth_score": 6,
      "shareholder_score": 5,
      "quality_score_detail": 6,
      "bonus_score": 1,
      "risk_penalty": -18,
      "forecast_adj": 0,
      "net_cash_ratio": 1.26,
      "per": 9.99,
      "market_cap_oku": 111.6,
      "dividend_yield": 3.96,
      "payout_ratio": 32.93,
      "roe": 4.69,
      "roic": 7.65,
      "pbr": 0.52,
      "ai_comment": "KFC LTD(日本)は3期連続増収を達成しており売上成長は継続しているが、直近期の営業利益は前期比-16.2%と大幅減益となっている。最新3Q累計でも営業利益は前年同期比-17.2%と悪化が続いており、収益性の低下が顕著。PBR0.52倍・PER約10倍と割安感はあるが、ROE4.69%と低水準でNC比も1.26と財務レバレッジへの注意が必要。外食・フードサービス業界は競争激化と原材料・人件費上昇が収益を圧迫しており、フランチャイズ運営の安定性はあるものの利益改善が課題。通期予想達成には4Q単独での利益回復が求められる状況。",
      "risk_checks": {
        "roe_15_percent": false,
        "equity_ratio_50_percent": false,
        "debt_to_profit_5x": true,
        "fcf_stability": false,
        "liquidity_risk": true,
        "one_time_profit_risk": false
      },
      "trend_score": 5,
      "quality_score": 4,
      "chart_signals": {
        "volume_surge": false,
        "above_ma": false,
        "near_high": true
      },
      "tenbagger_stars": 2,
      "tab": "general",
      "theoretical_price": 4027.0,
      "upside_percent": 165.4,
      "_source": "general"
    },
    {
      "code": "1420",
      "name": "SANYO HOMES CORPORATION",
      "name_jp": "サンヨーホームズ",
      "website": "https://www.sanyohomes.co.jp",
      "market": "スタンダード",
      "score": 20,
      "valuation_score": 16,
      "growth_score": 6,
      "shareholder_score": 6,
      "quality_score_detail": 1,
      "bonus_score": 1,
      "risk_penalty": -18,
      "forecast_adj": 2,
      "net_cash_ratio": 1.38,
      "per": 6.41,
      "market_cap_oku": 72.9,
      "dividend_yield": 4.05,
      "payout_ratio": 26.02,
      "roe": 4.39,
      "roic": 6.42,
      "pbr": 0.48,
      "ai_comment": "サンヨーホームズは住宅メーカーとして中堅規模を維持。直近四半期（3Q累計）では売上が前年比+7.5%と増収基調にあるが、営業利益は▲200M円と赤字で収益性に課題。通期予想は売上610億円・営業利益20億円と黒字回復を見込むが、3Q時点での赤字は懸念材料。過去3期の売上は409.7→458.6→455.2億円と概ね横ばい圏。PERは6.4倍・PBR0.48倍と割安感があるが、ROE4.39%と低水準。住宅業界は金利動向・資材コスト上昇・人口動態の影響を受けやすく競争も激しい。競争優位性は限定的で収益の安定性に乏しい点がリスク。",
      "risk_checks": {
        "roe_15_percent": false,
        "equity_ratio_50_percent": false,
        "debt_to_profit_5x": true,
        "fcf_stability": false,
        "liquidity_risk": true,
        "one_time_profit_risk": false
      },
      "trend_score": 4,
      "quality_score": 2,
      "chart_signals": {
        "volume_surge": false,
        "above_ma": false,
        "near_high": false
      },
      "tenbagger_stars": 2,
      "tab": "general",
      "theoretical_price": 1467.0,
      "upside_percent": 138.2,
      "_source": "general"
    },
    {
      "code": "6899",
      "name": "ASTI CORPORATION",
      "name_jp": "ＡＳＴＩ",
      "website": "https://www.asti.co.jp",
      "market": "スタンダード",
      "score": 12,
      "valuation_score": 14,
      "growth_score": 1,
      "shareholder_score": 8,
      "quality_score_detail": 1,
      "bonus_score": 2,
      "risk_penalty": -18,
      "forecast_adj": 0,
      "net_cash_ratio": 1.16,
      "per": 8.26,
      "market_cap_oku": 74.7,
      "dividend_yield": 4.45,
      "payout_ratio": 38.03,
      "roe": 2.55,
      "roic": 5.2,
      "pbr": 0.3,
      "ai_comment": "ASTI CORPORATIONは電子部品・車載向け事業を展開する技術系企業。直近3Qの四半期業績では売上-5.6%、営業利益-22.8%、純利益-18.9%と大幅悪化が顕著。通期予想も営業利益1000百万円と前期比で大幅減益見通し。過去3期の売上は648.8→636.1→654.4億円と横ばい推移だが、収益性は大きく低下。PBR0.3倍という超割安水準はバリュートラップの可能性もあり、ROE2.55%と資本効率が低い。競争環境は厳しく、車載部品市場での価格競争や顧客集中リスクが懸念される。PER8.3倍は低いが利益の質・安定性に課題があり、上方修正の可能性は低い。",
      "risk_checks": {
        "roe_15_percent": false,
        "equity_ratio_50_percent": false,
        "debt_to_profit_5x": true,
        "fcf_stability": false,
        "liquidity_risk": true,
        "one_time_profit_risk": false
      },
      "trend_score": 2,
      "quality_score": 2,
      "chart_signals": {
        "volume_surge": false,
        "above_ma": false,
        "near_high": false
      },
      "tenbagger_stars": 2,
      "tab": "general",
      "theoretical_price": 8478.0,
      "upside_percent": 254.9,
      "_source": "general"
    },
    {
      "code": "2788",
      "name": "APPLE INTERNATIONAL CO LTD",
      "name_jp": "アップルインターナショナル",
      "website": "https://www.apple-international.com",
      "market": "スタンダード",
      "score": 11,
      "valuation_score": 22,
      "growth_score": 0,
      "shareholder_score": 9,
      "quality_score_detail": 2,
      "bonus_score": 0,
      "risk_penalty": -26,
      "forecast_adj": 0,
      "net_cash_ratio": 2.17,
      "per": 5.45,
      "market_cap_oku": 42.8,
      "dividend_yield": 2.95,
      "payout_ratio": 16.37,
      "roe": 7.67,
      "roic": 7.64,
      "pbr": 0.42,
      "ai_comment": "APPLE INTERNATIONAL CO LTDは直近期（2025年12月期）において売上高408億円と前期比-6.8%、営業利益は568百万円で前期比-58.7%と大幅な減益を記録。過去3期の売上推移は309→438→408億円と増収後に反落しており、業績トレンドは悪化傾向。消費者向けシクリカルセクターに属し競争環境も厳しい。ROEは7.67%と低水準、PBR0.42倍と割安感はあるものの収益力の裏付けが乏しい。NC比2.17はキャッシュ創出力に一定の余地を示すが、営業利益率は1.4%程度と極めて薄利であり事業の質・参入障壁は平均以下と判断。PER5.4倍の割安評価はリスクを反映した結果とみられる。",
      "risk_checks": {
        "roe_15_percent": false,
        "equity_ratio_50_percent": false,
        "debt_to_profit_5x": false,
        "fcf_stability": false,
        "liquidity_risk": true,
        "one_time_profit_risk": false
      },
      "trend_score": 2,
      "quality_score": 2,
      "chart_signals": {
        "volume_surge": false,
        "above_ma": false,
        "near_high": true
      },
      "tenbagger_stars": 2,
      "tab": "general",
      "theoretical_price": 920.0,
      "upside_percent": 176.2,
      "_source": "general"
    },
    {
      "code": "7229",
      "name": "YUTAKA GIKEN CO",
      "name_jp": "ユタカ技研",
      "website": "https://www.yutakagiken.co.jp",
      "market": "スタンダード",
      "score": 10,
      "valuation_score": 14,
      "growth_score": 0,
      "shareholder_score": 6,
      "quality_score_detail": 5,
      "bonus_score": 1,
      "risk_penalty": -18,
      "forecast_adj": 0,
      "net_cash_ratio": 1.39,
      "per": 8.51,
      "market_cap_oku": 443.8,
      "dividend_yield": 2.4,
      "payout_ratio": 10.23,
      "roe": 4.45,
      "roic": 10.69,
      "pbr": 0.41,
      "ai_comment": "豊田合成系の自動車部品メーカーで、排気系部品を主力とする。直近3期の売上は2180→2163→1792億円と連続減収が続き、直近四半期（3Q）でも前年比売上▲6.6%・営業利益▲14.7%と悪化トレンドが継続。EV化による内燃機関部品需要の長期的な縮小リスクも深刻で、構造的な逆風に晒されている。PBRは0.41倍と割安感があるが、ROEは4.45%と低水準。NC比1.39はやや高めで財務余裕に限界も見られる。通期予想は減収減益見込みで、業績反転の兆しは薄い。競争優位性も限定的で、将来性に対する不確実性が高い状況が続く。",
      "risk_checks": {
        "roe_15_percent": false,
        "equity_ratio_50_percent": false,
        "debt_to_profit_5x": true,
        "fcf_stability": false,
        "liquidity_risk": true,
        "one_time_profit_risk": false
      },
      "trend_score": 0,
      "quality_score": 2,
      "chart_signals": {
        "volume_surge": false,
        "above_ma": false,
        "near_high": true
      },
      "tenbagger_stars": 1,
      "tab": "general",
      "theoretical_price": 8360.0,
      "upside_percent": 179.1,
      "_source": "general"
    },
    {
      "code": "5408",
      "name": "NAKAYAMA STEEL WORKS",
      "name_jp": "中山製鋼所",
      "website": "https://www.nakayama-steel.co.jp",
      "market": "プライム",
      "score": 6,
      "valuation_score": 17,
      "growth_score": 0,
      "shareholder_score": 5,
      "quality_score_detail": 7,
      "bonus_score": 1,
      "risk_penalty": -26,
      "forecast_adj": 0,
      "net_cash_ratio": 1.55,
      "per": 8.06,
      "market_cap_oku": 338.3,
      "dividend_yield": 1.63,
      "payout_ratio": 38.76,
      "roe": 5.33,
      "roic": 8.61,
      "pbr": 0.32,
      "ai_comment": "中山製鋼所は直近3期で売上が1885→1844→1693億円と連続減収、営業利益も前期比31.6%減と大幅悪化。さらに最新3Q累計では売上前年比▲15.4%、営業利益▲52.0%、純利益▲63.2%と急激な業績悪化が進行中。通期予想も営業利益42億円と低水準。鉄鋼セクターは需給悪化・鋼材価格軟化が直撃し、競争優位性は限定的。PBR0.32倍・PER8倍と割安感はあるがROE5.33%と低く、資本効率改善は道半ば。NC比1.55は中程度で財務的な極端なリスクはないが、収益回復の見通しが立ちにくい状況。上方修正の可能性も低く、短期的な投資魅力は乏しい。",
      "risk_checks": {
        "roe_15_percent": false,
        "equity_ratio_50_percent": false,
        "debt_to_profit_5x": false,
        "fcf_stability": false,
        "liquidity_risk": true,
        "one_time_profit_risk": false
      },
      "trend_score": 0,
      "quality_score": 2,
      "chart_signals": {
        "volume_surge": false,
        "above_ma": true,
        "near_high": true
      },
      "tenbagger_stars": 1,
      "tab": "general",
      "theoretical_price": 2536.0,
      "upside_percent": 306.5,
      "_source": "general"
    }
  ]
}